{
  "winner" : 6.0,
  "p1" : 6.0,
  "p2" : 6.0,
  "moves" : [
    {
      "simulations" : 7644,
      "stats" : [
        {
          "pts" : 144.0,
          "attempts" : 241
        },
        {
          "pts" : 141.0,
          "attempts" : 237
        },
        {
          "pts" : 139.5,
          "attempts" : 235
        },
        {
          "pts" : 128.5,
          "attempts" : 220
        },
        {
          "pts" : 128.0,
          "attempts" : 219
        },
        {
          "pts" : 127.0,
          "attempts" : 218
        },
        {
          "pts" : 123.5,
          "attempts" : 213
        },
        {
          "pts" : 121.0,
          "attempts" : 210
        },
        {
          "pts" : 114.0,
          "attempts" : 200
        },
        {
          "pts" : 112.0,
          "attempts" : 197
        },
        {
          "pts" : 110.0,
          "attempts" : 195
        },
        {
          "pts" : 105.5,
          "attempts" : 187
        },
        {
          "pts" : 102.0,
          "attempts" : 183
        },
        {
          "pts" : 100.5,
          "attempts" : 181
        },
        {
          "pts" : 98.5,
          "attempts" : 178
        },
        {
          "pts" : 95.0,
          "attempts" : 174
        },
        {
          "pts" : 94.5,
          "attempts" : 173
        },
        {
          "pts" : 91.0,
          "attempts" : 168
        },
        {
          "pts" : 90.0,
          "attempts" : 167
        },
        {
          "pts" : 89.5,
          "attempts" : 166
        },
        {
          "pts" : 86.5,
          "attempts" : 162
        },
        {
          "pts" : 86.5,
          "attempts" : 162
        },
        {
          "pts" : 86.0,
          "attempts" : 161
        },
        {
          "pts" : 86.0,
          "attempts" : 161
        },
        {
          "pts" : 80.5,
          "attempts" : 153
        },
        {
          "pts" : 78.5,
          "attempts" : 150
        },
        {
          "pts" : 74.0,
          "attempts" : 144
        },
        {
          "pts" : 70.0,
          "attempts" : 138
        },
        {
          "pts" : 69.5,
          "attempts" : 137
        },
        {
          "pts" : 69.0,
          "attempts" : 136
        },
        {
          "pts" : 68.0,
          "attempts" : 135
        },
        {
          "pts" : 67.0,
          "attempts" : 134
        },
        {
          "pts" : 67.5,
          "attempts" : 134
        },
        {
          "pts" : 64.5,
          "attempts" : 130
        },
        {
          "pts" : 63.0,
          "attempts" : 128
        },
        {
          "pts" : 63.5,
          "attempts" : 128
        },
        {
          "pts" : 63.5,
          "attempts" : 128
        },
        {
          "pts" : 62.0,
          "attempts" : 126
        },
        {
          "pts" : 57.0,
          "attempts" : 119
        },
        {
          "pts" : 56.0,
          "attempts" : 117
        },
        {
          "pts" : 54.0,
          "attempts" : 114
        },
        {
          "pts" : 54.0,
          "attempts" : 114
        },
        {
          "pts" : 50.5,
          "attempts" : 109
        },
        {
          "pts" : 48.5,
          "attempts" : 106
        },
        {
          "pts" : 48.5,
          "attempts" : 106
        },
        {
          "pts" : 45.0,
          "attempts" : 101
        },
        {
          "pts" : 35.0,
          "attempts" : 86
        },
        {
          "pts" : 35.0,
          "attempts" : 86
        },
        {
          "pts" : 29.5,
          "attempts" : 77
        }
      ]
    },
    {
      "simulations" : 7326,
      "stats" : [
        {
          "pts" : 124.5,
          "attempts" : 251
        },
        {
          "pts" : 116.0,
          "attempts" : 237
        },
        {
          "pts" : 109.0,
          "attempts" : 226
        },
        {
          "pts" : 108.0,
          "attempts" : 224
        },
        {
          "pts" : 98.5,
          "attempts" : 209
        },
        {
          "pts" : 96.0,
          "attempts" : 205
        },
        {
          "pts" : 96.0,
          "attempts" : 205
        },
        {
          "pts" : 92.5,
          "attempts" : 199
        },
        {
          "pts" : 91.0,
          "attempts" : 197
        },
        {
          "pts" : 81.5,
          "attempts" : 181
        },
        {
          "pts" : 81.0,
          "attempts" : 181
        },
        {
          "pts" : 80.0,
          "attempts" : 179
        },
        {
          "pts" : 79.5,
          "attempts" : 178
        },
        {
          "pts" : 79.5,
          "attempts" : 178
        },
        {
          "pts" : 79.0,
          "attempts" : 177
        },
        {
          "pts" : 78.0,
          "attempts" : 176
        },
        {
          "pts" : 78.0,
          "attempts" : 176
        },
        {
          "pts" : 79.5,
          "attempts" : 174
        },
        {
          "pts" : 73.5,
          "attempts" : 168
        },
        {
          "pts" : 69.5,
          "attempts" : 161
        },
        {
          "pts" : 64.0,
          "attempts" : 152
        },
        {
          "pts" : 63.5,
          "attempts" : 151
        },
        {
          "pts" : 63.5,
          "attempts" : 151
        },
        {
          "pts" : 62.0,
          "attempts" : 149
        },
        {
          "pts" : 60.5,
          "attempts" : 146
        },
        {
          "pts" : 59.0,
          "attempts" : 144
        },
        {
          "pts" : 58.5,
          "attempts" : 143
        },
        {
          "pts" : 57.0,
          "attempts" : 140
        },
        {
          "pts" : 57.0,
          "attempts" : 140
        },
        {
          "pts" : 57.0,
          "attempts" : 140
        },
        {
          "pts" : 52.0,
          "attempts" : 132
        },
        {
          "pts" : 51.0,
          "attempts" : 130
        },
        {
          "pts" : 50.5,
          "attempts" : 129
        },
        {
          "pts" : 50.0,
          "attempts" : 128
        },
        {
          "pts" : 50.0,
          "attempts" : 128
        },
        {
          "pts" : 48.5,
          "attempts" : 126
        },
        {
          "pts" : 48.5,
          "attempts" : 126
        },
        {
          "pts" : 47.5,
          "attempts" : 124
        },
        {
          "pts" : 46.0,
          "attempts" : 121
        },
        {
          "pts" : 43.5,
          "attempts" : 117
        },
        {
          "pts" : 38.0,
          "attempts" : 107
        },
        {
          "pts" : 35.5,
          "attempts" : 103
        },
        {
          "pts" : 34.0,
          "attempts" : 100
        },
        {
          "pts" : 33.5,
          "attempts" : 99
        },
        {
          "pts" : 30.5,
          "attempts" : 94
        },
        {
          "pts" : 28.0,
          "attempts" : 89
        },
        {
          "pts" : 21.0,
          "attempts" : 76
        },
        {
          "pts" : 12.5,
          "attempts" : 59
        }
      ]
    },
    {
      "simulations" : 8518,
      "stats" : [
        {
          "pts" : 202.5,
          "attempts" : 311
        },
        {
          "pts" : 196.0,
          "attempts" : 303
        },
        {
          "pts" : 187.5,
          "attempts" : 292
        },
        {
          "pts" : 153.5,
          "attempts" : 247
        },
        {
          "pts" : 148.5,
          "attempts" : 241
        },
        {
          "pts" : 144.5,
          "attempts" : 235
        },
        {
          "pts" : 139.5,
          "attempts" : 229
        },
        {
          "pts" : 137.5,
          "attempts" : 226
        },
        {
          "pts" : 135.5,
          "attempts" : 223
        },
        {
          "pts" : 128.0,
          "attempts" : 213
        },
        {
          "pts" : 127.5,
          "attempts" : 213
        },
        {
          "pts" : 128.0,
          "attempts" : 213
        },
        {
          "pts" : 120.5,
          "attempts" : 203
        },
        {
          "pts" : 117.0,
          "attempts" : 199
        },
        {
          "pts" : 114.5,
          "attempts" : 195
        },
        {
          "pts" : 105.0,
          "attempts" : 182
        },
        {
          "pts" : 104.0,
          "attempts" : 181
        },
        {
          "pts" : 104.0,
          "attempts" : 181
        },
        {
          "pts" : 103.5,
          "attempts" : 180
        },
        {
          "pts" : 102.0,
          "attempts" : 178
        },
        {
          "pts" : 100.5,
          "attempts" : 176
        },
        {
          "pts" : 99.5,
          "attempts" : 175
        },
        {
          "pts" : 99.0,
          "attempts" : 174
        },
        {
          "pts" : 97.0,
          "attempts" : 171
        },
        {
          "pts" : 97.0,
          "attempts" : 171
        },
        {
          "pts" : 97.0,
          "attempts" : 171
        },
        {
          "pts" : 96.0,
          "attempts" : 170
        },
        {
          "pts" : 96.0,
          "attempts" : 170
        },
        {
          "pts" : 95.0,
          "attempts" : 169
        },
        {
          "pts" : 90.5,
          "attempts" : 162
        },
        {
          "pts" : 90.5,
          "attempts" : 162
        },
        {
          "pts" : 89.5,
          "attempts" : 161
        },
        {
          "pts" : 86.5,
          "attempts" : 157
        },
        {
          "pts" : 85.5,
          "attempts" : 156
        },
        {
          "pts" : 84.5,
          "attempts" : 154
        },
        {
          "pts" : 83.0,
          "attempts" : 152
        },
        {
          "pts" : 82.0,
          "attempts" : 151
        },
        {
          "pts" : 76.5,
          "attempts" : 143
        },
        {
          "pts" : 74.5,
          "attempts" : 140
        },
        {
          "pts" : 71.5,
          "attempts" : 136
        },
        {
          "pts" : 71.0,
          "attempts" : 135
        },
        {
          "pts" : 70.0,
          "attempts" : 133
        },
        {
          "pts" : 67.5,
          "attempts" : 130
        },
        {
          "pts" : 64.5,
          "attempts" : 126
        },
        {
          "pts" : 63.0,
          "attempts" : 124
        },
        {
          "pts" : 50.5,
          "attempts" : 106
        },
        {
          "pts" : 45.0,
          "attempts" : 98
        }
      ]
    },
    {
      "simulations" : 8455,
      "stats" : [
        {
          "pts" : 221.0,
          "attempts" : 444
        },
        {
          "pts" : 121.0,
          "attempts" : 274
        },
        {
          "pts" : 108.5,
          "attempts" : 252
        },
        {
          "pts" : 104.5,
          "attempts" : 245
        },
        {
          "pts" : 104.5,
          "attempts" : 245
        },
        {
          "pts" : 97.5,
          "attempts" : 232
        },
        {
          "pts" : 91.0,
          "attempts" : 221
        },
        {
          "pts" : 90.0,
          "attempts" : 219
        },
        {
          "pts" : 81.0,
          "attempts" : 203
        },
        {
          "pts" : 80.5,
          "attempts" : 200
        },
        {
          "pts" : 78.5,
          "attempts" : 198
        },
        {
          "pts" : 78.5,
          "attempts" : 198
        },
        {
          "pts" : 78.5,
          "attempts" : 198
        },
        {
          "pts" : 75.0,
          "attempts" : 192
        },
        {
          "pts" : 74.5,
          "attempts" : 191
        },
        {
          "pts" : 72.0,
          "attempts" : 186
        },
        {
          "pts" : 71.0,
          "attempts" : 184
        },
        {
          "pts" : 70.5,
          "attempts" : 184
        },
        {
          "pts" : 70.0,
          "attempts" : 183
        },
        {
          "pts" : 69.5,
          "attempts" : 182
        },
        {
          "pts" : 68.5,
          "attempts" : 180
        },
        {
          "pts" : 68.0,
          "attempts" : 179
        },
        {
          "pts" : 66.5,
          "attempts" : 176
        },
        {
          "pts" : 66.0,
          "attempts" : 175
        },
        {
          "pts" : 66.0,
          "attempts" : 175
        },
        {
          "pts" : 63.0,
          "attempts" : 170
        },
        {
          "pts" : 62.5,
          "attempts" : 169
        },
        {
          "pts" : 61.5,
          "attempts" : 167
        },
        {
          "pts" : 61.0,
          "attempts" : 166
        },
        {
          "pts" : 60.0,
          "attempts" : 164
        },
        {
          "pts" : 59.0,
          "attempts" : 162
        },
        {
          "pts" : 58.5,
          "attempts" : 161
        },
        {
          "pts" : 58.0,
          "attempts" : 160
        },
        {
          "pts" : 57.0,
          "attempts" : 158
        },
        {
          "pts" : 56.5,
          "attempts" : 157
        },
        {
          "pts" : 55.5,
          "attempts" : 156
        },
        {
          "pts" : 56.0,
          "attempts" : 156
        },
        {
          "pts" : 55.0,
          "attempts" : 155
        },
        {
          "pts" : 53.0,
          "attempts" : 151
        },
        {
          "pts" : 49.5,
          "attempts" : 144
        },
        {
          "pts" : 49.0,
          "attempts" : 143
        },
        {
          "pts" : 44.5,
          "attempts" : 134
        },
        {
          "pts" : 44.0,
          "attempts" : 133
        },
        {
          "pts" : 36.0,
          "attempts" : 118
        },
        {
          "pts" : 34.0,
          "attempts" : 114
        },
        {
          "pts" : 27.5,
          "attempts" : 101
        }
      ]
    },
    {
      "simulations" : 8876,
      "stats" : [
        {
          "pts" : 244.0,
          "attempts" : 392
        },
        {
          "pts" : 230.0,
          "attempts" : 373
        },
        {
          "pts" : 199.5,
          "attempts" : 331
        },
        {
          "pts" : 164.5,
          "attempts" : 282
        },
        {
          "pts" : 158.5,
          "attempts" : 274
        },
        {
          "pts" : 158.0,
          "attempts" : 273
        },
        {
          "pts" : 156.5,
          "attempts" : 271
        },
        {
          "pts" : 154.5,
          "attempts" : 268
        },
        {
          "pts" : 140.0,
          "attempts" : 248
        },
        {
          "pts" : 139.0,
          "attempts" : 246
        },
        {
          "pts" : 135.0,
          "attempts" : 240
        },
        {
          "pts" : 125.0,
          "attempts" : 226
        },
        {
          "pts" : 119.5,
          "attempts" : 218
        },
        {
          "pts" : 115.5,
          "attempts" : 212
        },
        {
          "pts" : 114.0,
          "attempts" : 210
        },
        {
          "pts" : 114.0,
          "attempts" : 210
        },
        {
          "pts" : 113.5,
          "attempts" : 210
        },
        {
          "pts" : 114.0,
          "attempts" : 210
        },
        {
          "pts" : 110.0,
          "attempts" : 204
        },
        {
          "pts" : 106.5,
          "attempts" : 199
        },
        {
          "pts" : 99.5,
          "attempts" : 189
        },
        {
          "pts" : 98.5,
          "attempts" : 188
        },
        {
          "pts" : 95.5,
          "attempts" : 183
        },
        {
          "pts" : 94.5,
          "attempts" : 182
        },
        {
          "pts" : 91.5,
          "attempts" : 177
        },
        {
          "pts" : 88.0,
          "attempts" : 172
        },
        {
          "pts" : 87.0,
          "attempts" : 171
        },
        {
          "pts" : 87.0,
          "attempts" : 171
        },
        {
          "pts" : 85.0,
          "attempts" : 168
        },
        {
          "pts" : 84.5,
          "attempts" : 167
        },
        {
          "pts" : 84.5,
          "attempts" : 167
        },
        {
          "pts" : 81.0,
          "attempts" : 162
        },
        {
          "pts" : 75.0,
          "attempts" : 153
        },
        {
          "pts" : 72.5,
          "attempts" : 149
        },
        {
          "pts" : 72.0,
          "attempts" : 148
        },
        {
          "pts" : 68.5,
          "attempts" : 143
        },
        {
          "pts" : 64.5,
          "attempts" : 137
        },
        {
          "pts" : 63.5,
          "attempts" : 135
        },
        {
          "pts" : 63.0,
          "attempts" : 135
        },
        {
          "pts" : 60.0,
          "attempts" : 130
        },
        {
          "pts" : 59.0,
          "attempts" : 128
        },
        {
          "pts" : 58.0,
          "attempts" : 127
        },
        {
          "pts" : 43.0,
          "attempts" : 103
        },
        {
          "pts" : 42.5,
          "attempts" : 103
        },
        {
          "pts" : 35.5,
          "attempts" : 91
        }
      ]
    },
    {
      "simulations" : 8883,
      "stats" : [
        {
          "pts" : 266.0,
          "attempts" : 501
        },
        {
          "pts" : 218.5,
          "attempts" : 424
        },
        {
          "pts" : 153.5,
          "attempts" : 318
        },
        {
          "pts" : 129.5,
          "attempts" : 278
        },
        {
          "pts" : 128.5,
          "attempts" : 276
        },
        {
          "pts" : 122.5,
          "attempts" : 266
        },
        {
          "pts" : 117.5,
          "attempts" : 258
        },
        {
          "pts" : 105.5,
          "attempts" : 237
        },
        {
          "pts" : 104.5,
          "attempts" : 236
        },
        {
          "pts" : 102.0,
          "attempts" : 231
        },
        {
          "pts" : 100.0,
          "attempts" : 228
        },
        {
          "pts" : 94.0,
          "attempts" : 218
        },
        {
          "pts" : 94.0,
          "attempts" : 218
        },
        {
          "pts" : 92.5,
          "attempts" : 215
        },
        {
          "pts" : 91.0,
          "attempts" : 212
        },
        {
          "pts" : 88.5,
          "attempts" : 208
        },
        {
          "pts" : 82.5,
          "attempts" : 198
        },
        {
          "pts" : 78.5,
          "attempts" : 191
        },
        {
          "pts" : 78.5,
          "attempts" : 191
        },
        {
          "pts" : 79.0,
          "attempts" : 191
        },
        {
          "pts" : 77.0,
          "attempts" : 188
        },
        {
          "pts" : 75.5,
          "attempts" : 185
        },
        {
          "pts" : 73.5,
          "attempts" : 182
        },
        {
          "pts" : 70.5,
          "attempts" : 176
        },
        {
          "pts" : 70.5,
          "attempts" : 176
        },
        {
          "pts" : 70.0,
          "attempts" : 175
        },
        {
          "pts" : 69.5,
          "attempts" : 175
        },
        {
          "pts" : 67.0,
          "attempts" : 170
        },
        {
          "pts" : 66.0,
          "attempts" : 168
        },
        {
          "pts" : 64.0,
          "attempts" : 165
        },
        {
          "pts" : 64.0,
          "attempts" : 165
        },
        {
          "pts" : 63.0,
          "attempts" : 163
        },
        {
          "pts" : 62.5,
          "attempts" : 162
        },
        {
          "pts" : 61.5,
          "attempts" : 160
        },
        {
          "pts" : 62.0,
          "attempts" : 159
        },
        {
          "pts" : 58.0,
          "attempts" : 154
        },
        {
          "pts" : 56.5,
          "attempts" : 151
        },
        {
          "pts" : 55.5,
          "attempts" : 149
        },
        {
          "pts" : 55.0,
          "attempts" : 148
        },
        {
          "pts" : 49.5,
          "attempts" : 138
        },
        {
          "pts" : 49.0,
          "attempts" : 137
        },
        {
          "pts" : 40.0,
          "attempts" : 121
        },
        {
          "pts" : 37.0,
          "attempts" : 115
        },
        {
          "pts" : 32.5,
          "attempts" : 106
        }
      ]
    },
    {
      "simulations" : 8678,
      "stats" : [
        {
          "pts" : 546.5,
          "attempts" : 857
        },
        {
          "pts" : 284.5,
          "attempts" : 482
        },
        {
          "pts" : 146.5,
          "attempts" : 278
        },
        {
          "pts" : 134.0,
          "attempts" : 259
        },
        {
          "pts" : 133.5,
          "attempts" : 258
        },
        {
          "pts" : 131.0,
          "attempts" : 254
        },
        {
          "pts" : 122.5,
          "attempts" : 241
        },
        {
          "pts" : 122.0,
          "attempts" : 240
        },
        {
          "pts" : 120.5,
          "attempts" : 238
        },
        {
          "pts" : 119.5,
          "attempts" : 236
        },
        {
          "pts" : 119.5,
          "attempts" : 236
        },
        {
          "pts" : 113.0,
          "attempts" : 226
        },
        {
          "pts" : 106.5,
          "attempts" : 216
        },
        {
          "pts" : 102.5,
          "attempts" : 210
        },
        {
          "pts" : 102.5,
          "attempts" : 210
        },
        {
          "pts" : 102.0,
          "attempts" : 209
        },
        {
          "pts" : 99.0,
          "attempts" : 204
        },
        {
          "pts" : 95.0,
          "attempts" : 198
        },
        {
          "pts" : 84.5,
          "attempts" : 181
        },
        {
          "pts" : 81.0,
          "attempts" : 176
        },
        {
          "pts" : 81.0,
          "attempts" : 176
        },
        {
          "pts" : 78.0,
          "attempts" : 171
        },
        {
          "pts" : 76.0,
          "attempts" : 168
        },
        {
          "pts" : 75.0,
          "attempts" : 166
        },
        {
          "pts" : 75.0,
          "attempts" : 166
        },
        {
          "pts" : 74.5,
          "attempts" : 165
        },
        {
          "pts" : 72.5,
          "attempts" : 162
        },
        {
          "pts" : 72.5,
          "attempts" : 162
        },
        {
          "pts" : 72.0,
          "attempts" : 161
        },
        {
          "pts" : 69.0,
          "attempts" : 156
        },
        {
          "pts" : 63.5,
          "attempts" : 147
        },
        {
          "pts" : 60.5,
          "attempts" : 142
        },
        {
          "pts" : 59.0,
          "attempts" : 140
        },
        {
          "pts" : 58.0,
          "attempts" : 138
        },
        {
          "pts" : 56.0,
          "attempts" : 135
        },
        {
          "pts" : 55.0,
          "attempts" : 133
        },
        {
          "pts" : 54.5,
          "attempts" : 132
        },
        {
          "pts" : 51.5,
          "attempts" : 127
        },
        {
          "pts" : 48.5,
          "attempts" : 122
        },
        {
          "pts" : 47.5,
          "attempts" : 121
        },
        {
          "pts" : 40.5,
          "attempts" : 109
        },
        {
          "pts" : 30.0,
          "attempts" : 90
        },
        {
          "pts" : 24.5,
          "attempts" : 80
        }
      ]
    },
    {
      "simulations" : 9549,
      "stats" : [
        {
          "pts" : 358.5,
          "attempts" : 713
        },
        {
          "pts" : 259.5,
          "attempts" : 542
        },
        {
          "pts" : 212.5,
          "attempts" : 459
        },
        {
          "pts" : 178.0,
          "attempts" : 397
        },
        {
          "pts" : 154.5,
          "attempts" : 355
        },
        {
          "pts" : 100.5,
          "attempts" : 255
        },
        {
          "pts" : 95.0,
          "attempts" : 245
        },
        {
          "pts" : 94.0,
          "attempts" : 243
        },
        {
          "pts" : 93.5,
          "attempts" : 242
        },
        {
          "pts" : 91.0,
          "attempts" : 237
        },
        {
          "pts" : 89.0,
          "attempts" : 233
        },
        {
          "pts" : 88.0,
          "attempts" : 231
        },
        {
          "pts" : 87.5,
          "attempts" : 230
        },
        {
          "pts" : 83.5,
          "attempts" : 223
        },
        {
          "pts" : 84.0,
          "attempts" : 223
        },
        {
          "pts" : 82.5,
          "attempts" : 221
        },
        {
          "pts" : 81.0,
          "attempts" : 218
        },
        {
          "pts" : 80.0,
          "attempts" : 216
        },
        {
          "pts" : 78.0,
          "attempts" : 212
        },
        {
          "pts" : 77.0,
          "attempts" : 210
        },
        {
          "pts" : 75.5,
          "attempts" : 207
        },
        {
          "pts" : 74.0,
          "attempts" : 204
        },
        {
          "pts" : 70.5,
          "attempts" : 197
        },
        {
          "pts" : 70.5,
          "attempts" : 197
        },
        {
          "pts" : 70.5,
          "attempts" : 197
        },
        {
          "pts" : 70.5,
          "attempts" : 195
        },
        {
          "pts" : 69.0,
          "attempts" : 194
        },
        {
          "pts" : 65.0,
          "attempts" : 187
        },
        {
          "pts" : 64.5,
          "attempts" : 186
        },
        {
          "pts" : 64.5,
          "attempts" : 186
        },
        {
          "pts" : 63.5,
          "attempts" : 184
        },
        {
          "pts" : 57.0,
          "attempts" : 171
        },
        {
          "pts" : 55.5,
          "attempts" : 168
        },
        {
          "pts" : 50.0,
          "attempts" : 156
        },
        {
          "pts" : 49.0,
          "attempts" : 154
        },
        {
          "pts" : 47.5,
          "attempts" : 151
        },
        {
          "pts" : 45.5,
          "attempts" : 147
        },
        {
          "pts" : 40.5,
          "attempts" : 137
        },
        {
          "pts" : 28.5,
          "attempts" : 111
        },
        {
          "pts" : 27.5,
          "attempts" : 109
        },
        {
          "pts" : 27.0,
          "attempts" : 108
        },
        {
          "pts" : 22.5,
          "attempts" : 98
        }
      ]
    },
    {
      "simulations" : 10824,
      "stats" : [
        {
          "pts" : 678.5,
          "attempts" : 1009
        },
        {
          "pts" : 449.0,
          "attempts" : 697
        },
        {
          "pts" : 317.5,
          "attempts" : 514
        },
        {
          "pts" : 312.5,
          "attempts" : 507
        },
        {
          "pts" : 230.0,
          "attempts" : 390
        },
        {
          "pts" : 203.5,
          "attempts" : 352
        },
        {
          "pts" : 175.0,
          "attempts" : 311
        },
        {
          "pts" : 164.0,
          "attempts" : 295
        },
        {
          "pts" : 147.0,
          "attempts" : 270
        },
        {
          "pts" : 146.5,
          "attempts" : 269
        },
        {
          "pts" : 137.0,
          "attempts" : 255
        },
        {
          "pts" : 135.5,
          "attempts" : 253
        },
        {
          "pts" : 135.0,
          "attempts" : 252
        },
        {
          "pts" : 132.5,
          "attempts" : 248
        },
        {
          "pts" : 122.5,
          "attempts" : 233
        },
        {
          "pts" : 122.5,
          "attempts" : 233
        },
        {
          "pts" : 118.5,
          "attempts" : 227
        },
        {
          "pts" : 116.5,
          "attempts" : 224
        },
        {
          "pts" : 114.0,
          "attempts" : 221
        },
        {
          "pts" : 114.0,
          "attempts" : 221
        },
        {
          "pts" : 113.0,
          "attempts" : 219
        },
        {
          "pts" : 111.5,
          "attempts" : 217
        },
        {
          "pts" : 110.5,
          "attempts" : 215
        },
        {
          "pts" : 107.0,
          "attempts" : 210
        },
        {
          "pts" : 102.5,
          "attempts" : 203
        },
        {
          "pts" : 102.5,
          "attempts" : 203
        },
        {
          "pts" : 101.0,
          "attempts" : 201
        },
        {
          "pts" : 99.0,
          "attempts" : 198
        },
        {
          "pts" : 97.5,
          "attempts" : 196
        },
        {
          "pts" : 91.0,
          "attempts" : 186
        },
        {
          "pts" : 88.5,
          "attempts" : 182
        },
        {
          "pts" : 87.5,
          "attempts" : 180
        },
        {
          "pts" : 87.5,
          "attempts" : 180
        },
        {
          "pts" : 86.5,
          "attempts" : 179
        },
        {
          "pts" : 84.0,
          "attempts" : 175
        },
        {
          "pts" : 77.5,
          "attempts" : 165
        },
        {
          "pts" : 75.5,
          "attempts" : 162
        },
        {
          "pts" : 68.5,
          "attempts" : 151
        },
        {
          "pts" : 66.5,
          "attempts" : 147
        },
        {
          "pts" : 63.5,
          "attempts" : 143
        },
        {
          "pts" : 56.5,
          "attempts" : 131
        }
      ]
    },
    {
      "simulations" : 9397,
      "stats" : [
        {
          "pts" : 214.5,
          "attempts" : 526
        },
        {
          "pts" : 164.0,
          "attempts" : 424
        },
        {
          "pts" : 147.5,
          "attempts" : 390
        },
        {
          "pts" : 139.5,
          "attempts" : 374
        },
        {
          "pts" : 134.0,
          "attempts" : 363
        },
        {
          "pts" : 108.5,
          "attempts" : 309
        },
        {
          "pts" : 102.5,
          "attempts" : 297
        },
        {
          "pts" : 91.5,
          "attempts" : 273
        },
        {
          "pts" : 89.5,
          "attempts" : 269
        },
        {
          "pts" : 87.5,
          "attempts" : 264
        },
        {
          "pts" : 86.5,
          "attempts" : 262
        },
        {
          "pts" : 83.5,
          "attempts" : 256
        },
        {
          "pts" : 84.5,
          "attempts" : 250
        },
        {
          "pts" : 78.0,
          "attempts" : 244
        },
        {
          "pts" : 77.5,
          "attempts" : 243
        },
        {
          "pts" : 76.5,
          "attempts" : 241
        },
        {
          "pts" : 70.5,
          "attempts" : 227
        },
        {
          "pts" : 70.0,
          "attempts" : 226
        },
        {
          "pts" : 70.0,
          "attempts" : 226
        },
        {
          "pts" : 69.0,
          "attempts" : 224
        },
        {
          "pts" : 65.0,
          "attempts" : 215
        },
        {
          "pts" : 64.5,
          "attempts" : 214
        },
        {
          "pts" : 62.0,
          "attempts" : 208
        },
        {
          "pts" : 61.0,
          "attempts" : 206
        },
        {
          "pts" : 61.0,
          "attempts" : 206
        },
        {
          "pts" : 59.5,
          "attempts" : 203
        },
        {
          "pts" : 56.5,
          "attempts" : 196
        },
        {
          "pts" : 54.5,
          "attempts" : 191
        },
        {
          "pts" : 52.5,
          "attempts" : 187
        },
        {
          "pts" : 50.0,
          "attempts" : 181
        },
        {
          "pts" : 50.0,
          "attempts" : 181
        },
        {
          "pts" : 49.5,
          "attempts" : 180
        },
        {
          "pts" : 47.5,
          "attempts" : 175
        },
        {
          "pts" : 42.0,
          "attempts" : 163
        },
        {
          "pts" : 41.5,
          "attempts" : 162
        },
        {
          "pts" : 38.0,
          "attempts" : 153
        },
        {
          "pts" : 30.0,
          "attempts" : 134
        },
        {
          "pts" : 27.0,
          "attempts" : 127
        },
        {
          "pts" : 27.0,
          "attempts" : 127
        },
        {
          "pts" : 16.5,
          "attempts" : 100
        }
      ]
    },
    {
      "simulations" : 13003,
      "stats" : [
        {
          "pts" : 1070.0,
          "attempts" : 1493
        },
        {
          "pts" : 829.0,
          "attempts" : 1178
        },
        {
          "pts" : 788.5,
          "attempts" : 1127
        },
        {
          "pts" : 724.5,
          "attempts" : 1043
        },
        {
          "pts" : 228.0,
          "attempts" : 377
        },
        {
          "pts" : 217.0,
          "attempts" : 362
        },
        {
          "pts" : 214.5,
          "attempts" : 358
        },
        {
          "pts" : 211.5,
          "attempts" : 354
        },
        {
          "pts" : 201.5,
          "attempts" : 340
        },
        {
          "pts" : 178.5,
          "attempts" : 308
        },
        {
          "pts" : 158.5,
          "attempts" : 279
        },
        {
          "pts" : 158.0,
          "attempts" : 278
        },
        {
          "pts" : 154.5,
          "attempts" : 273
        },
        {
          "pts" : 153.5,
          "attempts" : 272
        },
        {
          "pts" : 145.5,
          "attempts" : 261
        },
        {
          "pts" : 141.0,
          "attempts" : 254
        },
        {
          "pts" : 137.0,
          "attempts" : 248
        },
        {
          "pts" : 135.5,
          "attempts" : 246
        },
        {
          "pts" : 135.0,
          "attempts" : 245
        },
        {
          "pts" : 135.0,
          "attempts" : 245
        },
        {
          "pts" : 133.5,
          "attempts" : 243
        },
        {
          "pts" : 130.0,
          "attempts" : 238
        },
        {
          "pts" : 129.5,
          "attempts" : 237
        },
        {
          "pts" : 122.5,
          "attempts" : 227
        },
        {
          "pts" : 122.5,
          "attempts" : 227
        },
        {
          "pts" : 115.0,
          "attempts" : 216
        },
        {
          "pts" : 113.0,
          "attempts" : 213
        },
        {
          "pts" : 105.5,
          "attempts" : 202
        },
        {
          "pts" : 102.5,
          "attempts" : 198
        },
        {
          "pts" : 101.0,
          "attempts" : 196
        },
        {
          "pts" : 98.0,
          "attempts" : 191
        },
        {
          "pts" : 96.5,
          "attempts" : 189
        },
        {
          "pts" : 80.0,
          "attempts" : 164
        },
        {
          "pts" : 60.0,
          "attempts" : 133
        },
        {
          "pts" : 52.5,
          "attempts" : 122
        },
        {
          "pts" : 51.0,
          "attempts" : 119
        },
        {
          "pts" : 51.0,
          "attempts" : 119
        },
        {
          "pts" : 48.5,
          "attempts" : 115
        },
        {
          "pts" : 47.0,
          "attempts" : 113
        }
      ]
    },
    {
      "simulations" : 11461,
      "stats" : [
        {
          "pts" : 281.5,
          "attempts" : 744
        },
        {
          "pts" : 280.5,
          "attempts" : 742
        },
        {
          "pts" : 255.5,
          "attempts" : 687
        },
        {
          "pts" : 173.0,
          "attempts" : 503
        },
        {
          "pts" : 114.5,
          "attempts" : 368
        },
        {
          "pts" : 108.0,
          "attempts" : 353
        },
        {
          "pts" : 100.5,
          "attempts" : 335
        },
        {
          "pts" : 99.5,
          "attempts" : 332
        },
        {
          "pts" : 97.0,
          "attempts" : 326
        },
        {
          "pts" : 90.5,
          "attempts" : 309
        },
        {
          "pts" : 84.0,
          "attempts" : 295
        },
        {
          "pts" : 80.5,
          "attempts" : 287
        },
        {
          "pts" : 76.5,
          "attempts" : 277
        },
        {
          "pts" : 73.5,
          "attempts" : 269
        },
        {
          "pts" : 72.5,
          "attempts" : 267
        },
        {
          "pts" : 71.5,
          "attempts" : 264
        },
        {
          "pts" : 71.0,
          "attempts" : 263
        },
        {
          "pts" : 70.0,
          "attempts" : 261
        },
        {
          "pts" : 70.0,
          "attempts" : 261
        },
        {
          "pts" : 69.5,
          "attempts" : 259
        },
        {
          "pts" : 69.5,
          "attempts" : 259
        },
        {
          "pts" : 68.0,
          "attempts" : 256
        },
        {
          "pts" : 66.0,
          "attempts" : 251
        },
        {
          "pts" : 64.5,
          "attempts" : 247
        },
        {
          "pts" : 63.5,
          "attempts" : 244
        },
        {
          "pts" : 62.0,
          "attempts" : 241
        },
        {
          "pts" : 62.0,
          "attempts" : 241
        },
        {
          "pts" : 60.5,
          "attempts" : 237
        },
        {
          "pts" : 55.5,
          "attempts" : 224
        },
        {
          "pts" : 55.5,
          "attempts" : 224
        },
        {
          "pts" : 54.0,
          "attempts" : 220
        },
        {
          "pts" : 53.5,
          "attempts" : 219
        },
        {
          "pts" : 49.5,
          "attempts" : 209
        },
        {
          "pts" : 48.0,
          "attempts" : 205
        },
        {
          "pts" : 47.5,
          "attempts" : 204
        },
        {
          "pts" : 46.5,
          "attempts" : 201
        },
        {
          "pts" : 46.0,
          "attempts" : 200
        },
        {
          "pts" : 37.5,
          "attempts" : 177
        }
      ]
    },
    {
      "simulations" : 110606,
      "stats" : [
        {
          "pts" : 53894.0,
          "attempts" : 53894
        },
        {
          "pts" : 53893.0,
          "attempts" : 53893
        },
        {
          "pts" : 103.5,
          "attempts" : 162
        },
        {
          "pts" : 99.0,
          "attempts" : 156
        },
        {
          "pts" : 68.0,
          "attempts" : 118
        },
        {
          "pts" : 55.5,
          "attempts" : 103
        },
        {
          "pts" : 49.5,
          "attempts" : 95
        },
        {
          "pts" : 49.0,
          "attempts" : 94
        },
        {
          "pts" : 47.5,
          "attempts" : 92
        },
        {
          "pts" : 45.5,
          "attempts" : 90
        },
        {
          "pts" : 44.0,
          "attempts" : 88
        },
        {
          "pts" : 44.5,
          "attempts" : 88
        },
        {
          "pts" : 44.5,
          "attempts" : 88
        },
        {
          "pts" : 42.5,
          "attempts" : 86
        },
        {
          "pts" : 43.0,
          "attempts" : 86
        },
        {
          "pts" : 41.0,
          "attempts" : 84
        },
        {
          "pts" : 41.5,
          "attempts" : 84
        },
        {
          "pts" : 38.0,
          "attempts" : 80
        },
        {
          "pts" : 37.5,
          "attempts" : 79
        },
        {
          "pts" : 37.0,
          "attempts" : 78
        },
        {
          "pts" : 35.5,
          "attempts" : 76
        },
        {
          "pts" : 35.5,
          "attempts" : 76
        },
        {
          "pts" : 33.5,
          "attempts" : 74
        },
        {
          "pts" : 34.0,
          "attempts" : 74
        },
        {
          "pts" : 31.5,
          "attempts" : 71
        },
        {
          "pts" : 31.5,
          "attempts" : 71
        },
        {
          "pts" : 31.0,
          "attempts" : 70
        },
        {
          "pts" : 30.0,
          "attempts" : 69
        },
        {
          "pts" : 24.5,
          "attempts" : 61
        },
        {
          "pts" : 24.5,
          "attempts" : 61
        },
        {
          "pts" : 22.5,
          "attempts" : 59
        },
        {
          "pts" : 22.0,
          "attempts" : 58
        },
        {
          "pts" : 22.0,
          "attempts" : 58
        },
        {
          "pts" : 21.0,
          "attempts" : 56
        },
        {
          "pts" : 19.5,
          "attempts" : 54
        },
        {
          "pts" : 16.5,
          "attempts" : 50
        },
        {
          "pts" : 4.0,
          "attempts" : 30
        }
      ]
    }
  ]
}