{
  "winner" : 6.0,
  "p1" : 6.0,
  "p2" : 6.0,
  "moves" : [
    {
      "simulations" : 11837,
      "stats" : [
        {
          "pts" : 171.0,
          "attempts" : 289
        },
        {
          "pts" : 167.5,
          "attempts" : 284
        },
        {
          "pts" : 164.5,
          "attempts" : 280
        },
        {
          "pts" : 159.5,
          "attempts" : 273
        },
        {
          "pts" : 156.0,
          "attempts" : 268
        },
        {
          "pts" : 151.5,
          "attempts" : 262
        },
        {
          "pts" : 152.0,
          "attempts" : 261
        },
        {
          "pts" : 146.0,
          "attempts" : 254
        },
        {
          "pts" : 143.5,
          "attempts" : 251
        },
        {
          "pts" : 141.5,
          "attempts" : 248
        },
        {
          "pts" : 132.5,
          "attempts" : 235
        },
        {
          "pts" : 132.5,
          "attempts" : 235
        },
        {
          "pts" : 129.0,
          "attempts" : 230
        },
        {
          "pts" : 125.0,
          "attempts" : 225
        },
        {
          "pts" : 124.0,
          "attempts" : 223
        },
        {
          "pts" : 123.5,
          "attempts" : 222
        },
        {
          "pts" : 120.5,
          "attempts" : 218
        },
        {
          "pts" : 120.0,
          "attempts" : 217
        },
        {
          "pts" : 116.5,
          "attempts" : 212
        },
        {
          "pts" : 115.5,
          "attempts" : 211
        },
        {
          "pts" : 113.5,
          "attempts" : 208
        },
        {
          "pts" : 113.0,
          "attempts" : 207
        },
        {
          "pts" : 104.0,
          "attempts" : 194
        },
        {
          "pts" : 104.0,
          "attempts" : 194
        },
        {
          "pts" : 102.0,
          "attempts" : 192
        },
        {
          "pts" : 100.5,
          "attempts" : 189
        },
        {
          "pts" : 100.0,
          "attempts" : 189
        },
        {
          "pts" : 95.5,
          "attempts" : 182
        },
        {
          "pts" : 95.0,
          "attempts" : 181
        },
        {
          "pts" : 92.5,
          "attempts" : 178
        },
        {
          "pts" : 92.5,
          "attempts" : 178
        },
        {
          "pts" : 92.0,
          "attempts" : 177
        },
        {
          "pts" : 92.0,
          "attempts" : 177
        },
        {
          "pts" : 90.5,
          "attempts" : 175
        },
        {
          "pts" : 90.5,
          "attempts" : 175
        },
        {
          "pts" : 87.0,
          "attempts" : 170
        },
        {
          "pts" : 86.5,
          "attempts" : 169
        },
        {
          "pts" : 86.5,
          "attempts" : 169
        },
        {
          "pts" : 84.5,
          "attempts" : 166
        },
        {
          "pts" : 84.5,
          "attempts" : 166
        },
        {
          "pts" : 83.5,
          "attempts" : 165
        },
        {
          "pts" : 83.0,
          "attempts" : 164
        },
        {
          "pts" : 82.5,
          "attempts" : 163
        },
        {
          "pts" : 79.0,
          "attempts" : 158
        },
        {
          "pts" : 77.5,
          "attempts" : 156
        },
        {
          "pts" : 78.0,
          "attempts" : 156
        },
        {
          "pts" : 77.0,
          "attempts" : 155
        },
        {
          "pts" : 77.0,
          "attempts" : 155
        },
        {
          "pts" : 76.5,
          "attempts" : 154
        },
        {
          "pts" : 74.0,
          "attempts" : 150
        },
        {
          "pts" : 71.0,
          "attempts" : 146
        },
        {
          "pts" : 69.5,
          "attempts" : 144
        },
        {
          "pts" : 66.5,
          "attempts" : 139
        },
        {
          "pts" : 62.5,
          "attempts" : 133
        },
        {
          "pts" : 62.0,
          "attempts" : 132
        },
        {
          "pts" : 61.0,
          "attempts" : 131
        },
        {
          "pts" : 58.5,
          "attempts" : 127
        },
        {
          "pts" : 58.5,
          "attempts" : 127
        },
        {
          "pts" : 57.5,
          "attempts" : 126
        },
        {
          "pts" : 54.0,
          "attempts" : 120
        },
        {
          "pts" : 46.0,
          "attempts" : 108
        },
        {
          "pts" : 42.0,
          "attempts" : 101
        },
        {
          "pts" : 39.0,
          "attempts" : 97
        },
        {
          "pts" : 38.5,
          "attempts" : 96
        }
      ]
    },
    {
      "simulations" : 10959,
      "stats" : [
        {
          "pts" : 175.5,
          "attempts" : 318
        },
        {
          "pts" : 161.0,
          "attempts" : 296
        },
        {
          "pts" : 147.0,
          "attempts" : 275
        },
        {
          "pts" : 143.0,
          "attempts" : 269
        },
        {
          "pts" : 132.5,
          "attempts" : 253
        },
        {
          "pts" : 126.5,
          "attempts" : 244
        },
        {
          "pts" : 118.0,
          "attempts" : 231
        },
        {
          "pts" : 112.0,
          "attempts" : 222
        },
        {
          "pts" : 111.5,
          "attempts" : 221
        },
        {
          "pts" : 111.0,
          "attempts" : 221
        },
        {
          "pts" : 110.0,
          "attempts" : 219
        },
        {
          "pts" : 103.0,
          "attempts" : 208
        },
        {
          "pts" : 102.5,
          "attempts" : 207
        },
        {
          "pts" : 100.0,
          "attempts" : 204
        },
        {
          "pts" : 101.0,
          "attempts" : 204
        },
        {
          "pts" : 99.5,
          "attempts" : 203
        },
        {
          "pts" : 99.5,
          "attempts" : 203
        },
        {
          "pts" : 99.0,
          "attempts" : 202
        },
        {
          "pts" : 98.0,
          "attempts" : 200
        },
        {
          "pts" : 96.0,
          "attempts" : 197
        },
        {
          "pts" : 95.5,
          "attempts" : 196
        },
        {
          "pts" : 88.5,
          "attempts" : 186
        },
        {
          "pts" : 89.0,
          "attempts" : 186
        },
        {
          "pts" : 86.0,
          "attempts" : 182
        },
        {
          "pts" : 86.5,
          "attempts" : 182
        },
        {
          "pts" : 85.5,
          "attempts" : 181
        },
        {
          "pts" : 84.5,
          "attempts" : 179
        },
        {
          "pts" : 84.0,
          "attempts" : 178
        },
        {
          "pts" : 83.0,
          "attempts" : 177
        },
        {
          "pts" : 83.0,
          "attempts" : 177
        },
        {
          "pts" : 83.0,
          "attempts" : 177
        },
        {
          "pts" : 82.5,
          "attempts" : 176
        },
        {
          "pts" : 78.0,
          "attempts" : 169
        },
        {
          "pts" : 75.0,
          "attempts" : 164
        },
        {
          "pts" : 72.0,
          "attempts" : 159
        },
        {
          "pts" : 71.0,
          "attempts" : 158
        },
        {
          "pts" : 70.0,
          "attempts" : 156
        },
        {
          "pts" : 69.0,
          "attempts" : 155
        },
        {
          "pts" : 69.0,
          "attempts" : 155
        },
        {
          "pts" : 69.5,
          "attempts" : 155
        },
        {
          "pts" : 68.0,
          "attempts" : 153
        },
        {
          "pts" : 67.0,
          "attempts" : 151
        },
        {
          "pts" : 65.0,
          "attempts" : 148
        },
        {
          "pts" : 64.0,
          "attempts" : 146
        },
        {
          "pts" : 63.0,
          "attempts" : 145
        },
        {
          "pts" : 59.0,
          "attempts" : 138
        },
        {
          "pts" : 57.0,
          "attempts" : 135
        },
        {
          "pts" : 56.5,
          "attempts" : 134
        },
        {
          "pts" : 56.0,
          "attempts" : 133
        },
        {
          "pts" : 55.5,
          "attempts" : 133
        },
        {
          "pts" : 54.0,
          "attempts" : 130
        },
        {
          "pts" : 51.0,
          "attempts" : 125
        },
        {
          "pts" : 50.5,
          "attempts" : 124
        },
        {
          "pts" : 49.5,
          "attempts" : 123
        },
        {
          "pts" : 49.5,
          "attempts" : 123
        },
        {
          "pts" : 48.5,
          "attempts" : 121
        },
        {
          "pts" : 47.5,
          "attempts" : 119
        },
        {
          "pts" : 44.5,
          "attempts" : 114
        },
        {
          "pts" : 41.0,
          "attempts" : 108
        },
        {
          "pts" : 40.5,
          "attempts" : 108
        },
        {
          "pts" : 38.0,
          "attempts" : 103
        },
        {
          "pts" : 37.0,
          "attempts" : 102
        },
        {
          "pts" : 35.0,
          "attempts" : 98
        }
      ]
    },
    {
      "simulations" : 11485,
      "stats" : [
        {
          "pts" : 180.0,
          "attempts" : 315
        },
        {
          "pts" : 177.0,
          "attempts" : 311
        },
        {
          "pts" : 169.5,
          "attempts" : 300
        },
        {
          "pts" : 148.0,
          "attempts" : 269
        },
        {
          "pts" : 148.0,
          "attempts" : 269
        },
        {
          "pts" : 143.5,
          "attempts" : 262
        },
        {
          "pts" : 134.5,
          "attempts" : 249
        },
        {
          "pts" : 132.0,
          "attempts" : 245
        },
        {
          "pts" : 130.0,
          "attempts" : 242
        },
        {
          "pts" : 126.0,
          "attempts" : 236
        },
        {
          "pts" : 126.0,
          "attempts" : 236
        },
        {
          "pts" : 125.5,
          "attempts" : 236
        },
        {
          "pts" : 123.0,
          "attempts" : 232
        },
        {
          "pts" : 122.5,
          "attempts" : 231
        },
        {
          "pts" : 120.5,
          "attempts" : 228
        },
        {
          "pts" : 115.5,
          "attempts" : 221
        },
        {
          "pts" : 113.0,
          "attempts" : 217
        },
        {
          "pts" : 109.0,
          "attempts" : 211
        },
        {
          "pts" : 107.5,
          "attempts" : 209
        },
        {
          "pts" : 107.0,
          "attempts" : 208
        },
        {
          "pts" : 105.5,
          "attempts" : 206
        },
        {
          "pts" : 105.5,
          "attempts" : 206
        },
        {
          "pts" : 104.0,
          "attempts" : 204
        },
        {
          "pts" : 103.0,
          "attempts" : 202
        },
        {
          "pts" : 97.0,
          "attempts" : 193
        },
        {
          "pts" : 95.5,
          "attempts" : 191
        },
        {
          "pts" : 94.0,
          "attempts" : 188
        },
        {
          "pts" : 92.5,
          "attempts" : 186
        },
        {
          "pts" : 92.5,
          "attempts" : 186
        },
        {
          "pts" : 92.5,
          "attempts" : 186
        },
        {
          "pts" : 88.0,
          "attempts" : 179
        },
        {
          "pts" : 80.0,
          "attempts" : 167
        },
        {
          "pts" : 79.5,
          "attempts" : 166
        },
        {
          "pts" : 78.5,
          "attempts" : 165
        },
        {
          "pts" : 78.5,
          "attempts" : 165
        },
        {
          "pts" : 78.0,
          "attempts" : 164
        },
        {
          "pts" : 76.0,
          "attempts" : 161
        },
        {
          "pts" : 75.5,
          "attempts" : 160
        },
        {
          "pts" : 75.0,
          "attempts" : 159
        },
        {
          "pts" : 73.5,
          "attempts" : 157
        },
        {
          "pts" : 73.5,
          "attempts" : 157
        },
        {
          "pts" : 72.0,
          "attempts" : 155
        },
        {
          "pts" : 70.0,
          "attempts" : 151
        },
        {
          "pts" : 69.0,
          "attempts" : 150
        },
        {
          "pts" : 69.0,
          "attempts" : 150
        },
        {
          "pts" : 68.5,
          "attempts" : 149
        },
        {
          "pts" : 68.5,
          "attempts" : 149
        },
        {
          "pts" : 66.5,
          "attempts" : 146
        },
        {
          "pts" : 66.0,
          "attempts" : 145
        },
        {
          "pts" : 65.0,
          "attempts" : 144
        },
        {
          "pts" : 65.5,
          "attempts" : 144
        },
        {
          "pts" : 64.0,
          "attempts" : 142
        },
        {
          "pts" : 59.0,
          "attempts" : 134
        },
        {
          "pts" : 59.0,
          "attempts" : 134
        },
        {
          "pts" : 58.5,
          "attempts" : 133
        },
        {
          "pts" : 58.0,
          "attempts" : 133
        },
        {
          "pts" : 57.5,
          "attempts" : 132
        },
        {
          "pts" : 55.5,
          "attempts" : 129
        },
        {
          "pts" : 54.0,
          "attempts" : 126
        },
        {
          "pts" : 35.0,
          "attempts" : 95
        },
        {
          "pts" : 30.5,
          "attempts" : 87
        },
        {
          "pts" : 27.5,
          "attempts" : 82
        }
      ]
    },
    {
      "simulations" : 12199,
      "stats" : [
        {
          "pts" : 205.5,
          "attempts" : 371
        },
        {
          "pts" : 184.5,
          "attempts" : 340
        },
        {
          "pts" : 176.0,
          "attempts" : 327
        },
        {
          "pts" : 169.0,
          "attempts" : 316
        },
        {
          "pts" : 169.0,
          "attempts" : 315
        },
        {
          "pts" : 151.5,
          "attempts" : 289
        },
        {
          "pts" : 149.5,
          "attempts" : 286
        },
        {
          "pts" : 139.0,
          "attempts" : 270
        },
        {
          "pts" : 134.0,
          "attempts" : 262
        },
        {
          "pts" : 127.0,
          "attempts" : 251
        },
        {
          "pts" : 123.5,
          "attempts" : 246
        },
        {
          "pts" : 123.0,
          "attempts" : 245
        },
        {
          "pts" : 122.0,
          "attempts" : 244
        },
        {
          "pts" : 121.0,
          "attempts" : 242
        },
        {
          "pts" : 120.5,
          "attempts" : 241
        },
        {
          "pts" : 120.0,
          "attempts" : 241
        },
        {
          "pts" : 119.5,
          "attempts" : 240
        },
        {
          "pts" : 109.5,
          "attempts" : 224
        },
        {
          "pts" : 107.5,
          "attempts" : 221
        },
        {
          "pts" : 104.0,
          "attempts" : 215
        },
        {
          "pts" : 101.5,
          "attempts" : 211
        },
        {
          "pts" : 100.5,
          "attempts" : 210
        },
        {
          "pts" : 100.5,
          "attempts" : 210
        },
        {
          "pts" : 100.0,
          "attempts" : 209
        },
        {
          "pts" : 99.5,
          "attempts" : 208
        },
        {
          "pts" : 98.0,
          "attempts" : 206
        },
        {
          "pts" : 96.5,
          "attempts" : 203
        },
        {
          "pts" : 96.5,
          "attempts" : 203
        },
        {
          "pts" : 92.0,
          "attempts" : 196
        },
        {
          "pts" : 90.5,
          "attempts" : 194
        },
        {
          "pts" : 90.0,
          "attempts" : 193
        },
        {
          "pts" : 84.0,
          "attempts" : 183
        },
        {
          "pts" : 83.0,
          "attempts" : 182
        },
        {
          "pts" : 82.5,
          "attempts" : 181
        },
        {
          "pts" : 80.5,
          "attempts" : 178
        },
        {
          "pts" : 79.5,
          "attempts" : 176
        },
        {
          "pts" : 78.0,
          "attempts" : 174
        },
        {
          "pts" : 76.5,
          "attempts" : 171
        },
        {
          "pts" : 76.0,
          "attempts" : 170
        },
        {
          "pts" : 73.0,
          "attempts" : 166
        },
        {
          "pts" : 73.5,
          "attempts" : 166
        },
        {
          "pts" : 71.0,
          "attempts" : 162
        },
        {
          "pts" : 69.5,
          "attempts" : 160
        },
        {
          "pts" : 69.0,
          "attempts" : 159
        },
        {
          "pts" : 68.0,
          "attempts" : 157
        },
        {
          "pts" : 67.0,
          "attempts" : 156
        },
        {
          "pts" : 65.5,
          "attempts" : 153
        },
        {
          "pts" : 64.5,
          "attempts" : 152
        },
        {
          "pts" : 65.0,
          "attempts" : 152
        },
        {
          "pts" : 63.0,
          "attempts" : 149
        },
        {
          "pts" : 61.5,
          "attempts" : 147
        },
        {
          "pts" : 58.0,
          "attempts" : 141
        },
        {
          "pts" : 57.5,
          "attempts" : 140
        },
        {
          "pts" : 56.5,
          "attempts" : 138
        },
        {
          "pts" : 55.5,
          "attempts" : 137
        },
        {
          "pts" : 54.5,
          "attempts" : 135
        },
        {
          "pts" : 54.0,
          "attempts" : 134
        },
        {
          "pts" : 52.5,
          "attempts" : 131
        },
        {
          "pts" : 44.5,
          "attempts" : 118
        },
        {
          "pts" : 40.0,
          "attempts" : 110
        },
        {
          "pts" : 30.0,
          "attempts" : 92
        }
      ]
    },
    {
      "simulations" : 11300,
      "stats" : [
        {
          "pts" : 300.0,
          "attempts" : 475
        },
        {
          "pts" : 244.5,
          "attempts" : 398
        },
        {
          "pts" : 161.5,
          "attempts" : 282
        },
        {
          "pts" : 152.5,
          "attempts" : 269
        },
        {
          "pts" : 136.5,
          "attempts" : 246
        },
        {
          "pts" : 136.0,
          "attempts" : 245
        },
        {
          "pts" : 134.5,
          "attempts" : 243
        },
        {
          "pts" : 131.5,
          "attempts" : 239
        },
        {
          "pts" : 128.0,
          "attempts" : 234
        },
        {
          "pts" : 126.5,
          "attempts" : 232
        },
        {
          "pts" : 122.0,
          "attempts" : 225
        },
        {
          "pts" : 121.5,
          "attempts" : 224
        },
        {
          "pts" : 120.0,
          "attempts" : 222
        },
        {
          "pts" : 119.5,
          "attempts" : 222
        },
        {
          "pts" : 119.5,
          "attempts" : 221
        },
        {
          "pts" : 118.5,
          "attempts" : 220
        },
        {
          "pts" : 116.0,
          "attempts" : 216
        },
        {
          "pts" : 114.0,
          "attempts" : 213
        },
        {
          "pts" : 107.5,
          "attempts" : 204
        },
        {
          "pts" : 103.5,
          "attempts" : 198
        },
        {
          "pts" : 103.0,
          "attempts" : 197
        },
        {
          "pts" : 103.0,
          "attempts" : 197
        },
        {
          "pts" : 101.0,
          "attempts" : 194
        },
        {
          "pts" : 100.0,
          "attempts" : 193
        },
        {
          "pts" : 99.0,
          "attempts" : 191
        },
        {
          "pts" : 98.0,
          "attempts" : 190
        },
        {
          "pts" : 98.0,
          "attempts" : 190
        },
        {
          "pts" : 97.5,
          "attempts" : 189
        },
        {
          "pts" : 97.0,
          "attempts" : 188
        },
        {
          "pts" : 95.0,
          "attempts" : 185
        },
        {
          "pts" : 94.0,
          "attempts" : 184
        },
        {
          "pts" : 90.5,
          "attempts" : 179
        },
        {
          "pts" : 89.5,
          "attempts" : 177
        },
        {
          "pts" : 89.0,
          "attempts" : 176
        },
        {
          "pts" : 86.5,
          "attempts" : 173
        },
        {
          "pts" : 86.5,
          "attempts" : 173
        },
        {
          "pts" : 85.5,
          "attempts" : 171
        },
        {
          "pts" : 83.5,
          "attempts" : 168
        },
        {
          "pts" : 83.0,
          "attempts" : 167
        },
        {
          "pts" : 82.0,
          "attempts" : 166
        },
        {
          "pts" : 73.0,
          "attempts" : 152
        },
        {
          "pts" : 72.5,
          "attempts" : 152
        },
        {
          "pts" : 72.0,
          "attempts" : 151
        },
        {
          "pts" : 72.0,
          "attempts" : 151
        },
        {
          "pts" : 69.0,
          "attempts" : 146
        },
        {
          "pts" : 68.5,
          "attempts" : 145
        },
        {
          "pts" : 63.5,
          "attempts" : 138
        },
        {
          "pts" : 63.0,
          "attempts" : 137
        },
        {
          "pts" : 62.0,
          "attempts" : 135
        },
        {
          "pts" : 61.0,
          "attempts" : 134
        },
        {
          "pts" : 60.0,
          "attempts" : 132
        },
        {
          "pts" : 59.5,
          "attempts" : 132
        },
        {
          "pts" : 55.5,
          "attempts" : 125
        },
        {
          "pts" : 55.5,
          "attempts" : 125
        },
        {
          "pts" : 54.0,
          "attempts" : 123
        },
        {
          "pts" : 51.0,
          "attempts" : 118
        },
        {
          "pts" : 47.5,
          "attempts" : 113
        },
        {
          "pts" : 48.0,
          "attempts" : 113
        },
        {
          "pts" : 41.0,
          "attempts" : 102
        },
        {
          "pts" : 39.5,
          "attempts" : 100
        }
      ]
    },
    {
      "simulations" : 11838,
      "stats" : [
        {
          "pts" : 242.0,
          "attempts" : 492
        },
        {
          "pts" : 140.5,
          "attempts" : 317
        },
        {
          "pts" : 138.0,
          "attempts" : 312
        },
        {
          "pts" : 119.5,
          "attempts" : 279
        },
        {
          "pts" : 116.0,
          "attempts" : 273
        },
        {
          "pts" : 109.5,
          "attempts" : 261
        },
        {
          "pts" : 104.0,
          "attempts" : 251
        },
        {
          "pts" : 104.0,
          "attempts" : 251
        },
        {
          "pts" : 101.0,
          "attempts" : 246
        },
        {
          "pts" : 99.0,
          "attempts" : 242
        },
        {
          "pts" : 98.5,
          "attempts" : 241
        },
        {
          "pts" : 97.5,
          "attempts" : 240
        },
        {
          "pts" : 97.0,
          "attempts" : 239
        },
        {
          "pts" : 93.5,
          "attempts" : 232
        },
        {
          "pts" : 93.0,
          "attempts" : 231
        },
        {
          "pts" : 92.5,
          "attempts" : 230
        },
        {
          "pts" : 90.5,
          "attempts" : 227
        },
        {
          "pts" : 89.0,
          "attempts" : 224
        },
        {
          "pts" : 87.0,
          "attempts" : 220
        },
        {
          "pts" : 86.5,
          "attempts" : 219
        },
        {
          "pts" : 84.5,
          "attempts" : 216
        },
        {
          "pts" : 83.5,
          "attempts" : 214
        },
        {
          "pts" : 82.5,
          "attempts" : 212
        },
        {
          "pts" : 83.5,
          "attempts" : 210
        },
        {
          "pts" : 80.0,
          "attempts" : 207
        },
        {
          "pts" : 78.5,
          "attempts" : 205
        },
        {
          "pts" : 79.0,
          "attempts" : 205
        },
        {
          "pts" : 76.5,
          "attempts" : 201
        },
        {
          "pts" : 75.5,
          "attempts" : 199
        },
        {
          "pts" : 75.0,
          "attempts" : 198
        },
        {
          "pts" : 74.5,
          "attempts" : 197
        },
        {
          "pts" : 72.5,
          "attempts" : 193
        },
        {
          "pts" : 72.0,
          "attempts" : 192
        },
        {
          "pts" : 71.0,
          "attempts" : 190
        },
        {
          "pts" : 70.0,
          "attempts" : 189
        },
        {
          "pts" : 66.5,
          "attempts" : 182
        },
        {
          "pts" : 66.5,
          "attempts" : 182
        },
        {
          "pts" : 66.0,
          "attempts" : 181
        },
        {
          "pts" : 65.5,
          "attempts" : 180
        },
        {
          "pts" : 65.0,
          "attempts" : 179
        },
        {
          "pts" : 62.5,
          "attempts" : 174
        },
        {
          "pts" : 57.0,
          "attempts" : 164
        },
        {
          "pts" : 57.0,
          "attempts" : 164
        },
        {
          "pts" : 54.0,
          "attempts" : 158
        },
        {
          "pts" : 53.5,
          "attempts" : 157
        },
        {
          "pts" : 50.0,
          "attempts" : 150
        },
        {
          "pts" : 49.5,
          "attempts" : 149
        },
        {
          "pts" : 49.0,
          "attempts" : 148
        },
        {
          "pts" : 49.0,
          "attempts" : 148
        },
        {
          "pts" : 47.0,
          "attempts" : 144
        },
        {
          "pts" : 44.5,
          "attempts" : 139
        },
        {
          "pts" : 42.0,
          "attempts" : 134
        },
        {
          "pts" : 41.0,
          "attempts" : 132
        },
        {
          "pts" : 41.0,
          "attempts" : 132
        },
        {
          "pts" : 39.5,
          "attempts" : 129
        },
        {
          "pts" : 37.5,
          "attempts" : 125
        },
        {
          "pts" : 33.5,
          "attempts" : 117
        },
        {
          "pts" : 32.0,
          "attempts" : 114
        },
        {
          "pts" : 25.5,
          "attempts" : 101
        }
      ]
    },
    {
      "simulations" : 6145,
      "stats" : [
        {
          "pts" : 141.5,
          "attempts" : 207
        },
        {
          "pts" : 118.0,
          "attempts" : 179
        },
        {
          "pts" : 114.0,
          "attempts" : 174
        },
        {
          "pts" : 110.0,
          "attempts" : 169
        },
        {
          "pts" : 98.0,
          "attempts" : 154
        },
        {
          "pts" : 97.0,
          "attempts" : 153
        },
        {
          "pts" : 88.5,
          "attempts" : 142
        },
        {
          "pts" : 87.0,
          "attempts" : 140
        },
        {
          "pts" : 86.5,
          "attempts" : 140
        },
        {
          "pts" : 82.5,
          "attempts" : 135
        },
        {
          "pts" : 82.0,
          "attempts" : 134
        },
        {
          "pts" : 76.5,
          "attempts" : 127
        },
        {
          "pts" : 75.0,
          "attempts" : 125
        },
        {
          "pts" : 72.0,
          "attempts" : 122
        },
        {
          "pts" : 71.0,
          "attempts" : 120
        },
        {
          "pts" : 70.5,
          "attempts" : 120
        },
        {
          "pts" : 71.0,
          "attempts" : 120
        },
        {
          "pts" : 70.0,
          "attempts" : 119
        },
        {
          "pts" : 69.5,
          "attempts" : 118
        },
        {
          "pts" : 68.5,
          "attempts" : 117
        },
        {
          "pts" : 67.5,
          "attempts" : 115
        },
        {
          "pts" : 67.0,
          "attempts" : 115
        },
        {
          "pts" : 64.5,
          "attempts" : 112
        },
        {
          "pts" : 64.5,
          "attempts" : 112
        },
        {
          "pts" : 63.0,
          "attempts" : 110
        },
        {
          "pts" : 61.5,
          "attempts" : 108
        },
        {
          "pts" : 60.0,
          "attempts" : 106
        },
        {
          "pts" : 59.5,
          "attempts" : 105
        },
        {
          "pts" : 58.5,
          "attempts" : 104
        },
        {
          "pts" : 56.0,
          "attempts" : 101
        },
        {
          "pts" : 55.0,
          "attempts" : 100
        },
        {
          "pts" : 51.5,
          "attempts" : 95
        },
        {
          "pts" : 50.5,
          "attempts" : 94
        },
        {
          "pts" : 50.0,
          "attempts" : 93
        },
        {
          "pts" : 47.0,
          "attempts" : 89
        },
        {
          "pts" : 46.0,
          "attempts" : 88
        },
        {
          "pts" : 45.0,
          "attempts" : 86
        },
        {
          "pts" : 43.5,
          "attempts" : 84
        },
        {
          "pts" : 42.0,
          "attempts" : 82
        },
        {
          "pts" : 42.0,
          "attempts" : 82
        },
        {
          "pts" : 42.0,
          "attempts" : 82
        },
        {
          "pts" : 41.5,
          "attempts" : 82
        },
        {
          "pts" : 41.0,
          "attempts" : 81
        },
        {
          "pts" : 40.5,
          "attempts" : 80
        },
        {
          "pts" : 40.0,
          "attempts" : 80
        },
        {
          "pts" : 38.5,
          "attempts" : 78
        },
        {
          "pts" : 39.0,
          "attempts" : 78
        },
        {
          "pts" : 39.0,
          "attempts" : 78
        },
        {
          "pts" : 39.0,
          "attempts" : 78
        },
        {
          "pts" : 39.0,
          "attempts" : 78
        },
        {
          "pts" : 37.5,
          "attempts" : 76
        },
        {
          "pts" : 36.0,
          "attempts" : 74
        },
        {
          "pts" : 35.0,
          "attempts" : 73
        },
        {
          "pts" : 34.5,
          "attempts" : 72
        },
        {
          "pts" : 31.0,
          "attempts" : 67
        },
        {
          "pts" : 31.0,
          "attempts" : 67
        },
        {
          "pts" : 28.0,
          "attempts" : 63
        },
        {
          "pts" : 27.5,
          "attempts" : 62
        }
      ]
    },
    {
      "simulations" : 8914,
      "stats" : [
        {
          "pts" : 435.5,
          "attempts" : 798
        },
        {
          "pts" : 143.5,
          "attempts" : 315
        },
        {
          "pts" : 82.0,
          "attempts" : 206
        },
        {
          "pts" : 76.5,
          "attempts" : 196
        },
        {
          "pts" : 75.5,
          "attempts" : 194
        },
        {
          "pts" : 72.5,
          "attempts" : 188
        },
        {
          "pts" : 69.0,
          "attempts" : 182
        },
        {
          "pts" : 68.0,
          "attempts" : 180
        },
        {
          "pts" : 66.0,
          "attempts" : 176
        },
        {
          "pts" : 65.5,
          "attempts" : 175
        },
        {
          "pts" : 65.0,
          "attempts" : 175
        },
        {
          "pts" : 64.5,
          "attempts" : 174
        },
        {
          "pts" : 64.0,
          "attempts" : 173
        },
        {
          "pts" : 59.0,
          "attempts" : 163
        },
        {
          "pts" : 57.0,
          "attempts" : 159
        },
        {
          "pts" : 56.0,
          "attempts" : 158
        },
        {
          "pts" : 56.0,
          "attempts" : 158
        },
        {
          "pts" : 54.5,
          "attempts" : 155
        },
        {
          "pts" : 54.0,
          "attempts" : 154
        },
        {
          "pts" : 53.5,
          "attempts" : 153
        },
        {
          "pts" : 53.5,
          "attempts" : 153
        },
        {
          "pts" : 53.0,
          "attempts" : 152
        },
        {
          "pts" : 52.5,
          "attempts" : 151
        },
        {
          "pts" : 51.5,
          "attempts" : 149
        },
        {
          "pts" : 51.5,
          "attempts" : 149
        },
        {
          "pts" : 51.0,
          "attempts" : 148
        },
        {
          "pts" : 50.0,
          "attempts" : 146
        },
        {
          "pts" : 49.5,
          "attempts" : 145
        },
        {
          "pts" : 48.0,
          "attempts" : 142
        },
        {
          "pts" : 47.0,
          "attempts" : 140
        },
        {
          "pts" : 46.0,
          "attempts" : 138
        },
        {
          "pts" : 46.0,
          "attempts" : 138
        },
        {
          "pts" : 45.0,
          "attempts" : 136
        },
        {
          "pts" : 44.5,
          "attempts" : 135
        },
        {
          "pts" : 44.0,
          "attempts" : 134
        },
        {
          "pts" : 43.5,
          "attempts" : 134
        },
        {
          "pts" : 42.5,
          "attempts" : 132
        },
        {
          "pts" : 42.5,
          "attempts" : 132
        },
        {
          "pts" : 42.5,
          "attempts" : 132
        },
        {
          "pts" : 41.5,
          "attempts" : 130
        },
        {
          "pts" : 41.5,
          "attempts" : 130
        },
        {
          "pts" : 44.0,
          "attempts" : 130
        },
        {
          "pts" : 41.0,
          "attempts" : 129
        },
        {
          "pts" : 38.5,
          "attempts" : 124
        },
        {
          "pts" : 38.5,
          "attempts" : 124
        },
        {
          "pts" : 38.0,
          "attempts" : 123
        },
        {
          "pts" : 37.0,
          "attempts" : 121
        },
        {
          "pts" : 37.0,
          "attempts" : 121
        },
        {
          "pts" : 34.5,
          "attempts" : 116
        },
        {
          "pts" : 32.0,
          "attempts" : 111
        },
        {
          "pts" : 31.0,
          "attempts" : 109
        },
        {
          "pts" : 27.0,
          "attempts" : 100
        },
        {
          "pts" : 24.5,
          "attempts" : 95
        },
        {
          "pts" : 23.0,
          "attempts" : 92
        },
        {
          "pts" : 21.0,
          "attempts" : 88
        },
        {
          "pts" : 17.0,
          "attempts" : 79
        },
        {
          "pts" : 14.5,
          "attempts" : 74
        }
      ]
    },
    {
      "simulations" : 7705,
      "stats" : [
        {
          "pts" : 159.0,
          "attempts" : 269
        },
        {
          "pts" : 151.0,
          "attempts" : 258
        },
        {
          "pts" : 138.0,
          "attempts" : 240
        },
        {
          "pts" : 132.5,
          "attempts" : 232
        },
        {
          "pts" : 114.0,
          "attempts" : 206
        },
        {
          "pts" : 99.5,
          "attempts" : 185
        },
        {
          "pts" : 98.0,
          "attempts" : 183
        },
        {
          "pts" : 96.5,
          "attempts" : 181
        },
        {
          "pts" : 85.5,
          "attempts" : 165
        },
        {
          "pts" : 85.0,
          "attempts" : 164
        },
        {
          "pts" : 83.0,
          "attempts" : 161
        },
        {
          "pts" : 81.5,
          "attempts" : 159
        },
        {
          "pts" : 81.5,
          "attempts" : 159
        },
        {
          "pts" : 81.0,
          "attempts" : 158
        },
        {
          "pts" : 76.5,
          "attempts" : 152
        },
        {
          "pts" : 76.5,
          "attempts" : 152
        },
        {
          "pts" : 75.0,
          "attempts" : 150
        },
        {
          "pts" : 75.5,
          "attempts" : 150
        },
        {
          "pts" : 75.5,
          "attempts" : 150
        },
        {
          "pts" : 74.5,
          "attempts" : 149
        },
        {
          "pts" : 73.5,
          "attempts" : 147
        },
        {
          "pts" : 70.5,
          "attempts" : 143
        },
        {
          "pts" : 70.0,
          "attempts" : 142
        },
        {
          "pts" : 69.0,
          "attempts" : 141
        },
        {
          "pts" : 68.5,
          "attempts" : 140
        },
        {
          "pts" : 68.0,
          "attempts" : 139
        },
        {
          "pts" : 66.5,
          "attempts" : 137
        },
        {
          "pts" : 66.5,
          "attempts" : 137
        },
        {
          "pts" : 65.5,
          "attempts" : 136
        },
        {
          "pts" : 65.5,
          "attempts" : 136
        },
        {
          "pts" : 60.0,
          "attempts" : 127
        },
        {
          "pts" : 59.5,
          "attempts" : 126
        },
        {
          "pts" : 59.0,
          "attempts" : 126
        },
        {
          "pts" : 58.0,
          "attempts" : 124
        },
        {
          "pts" : 58.0,
          "attempts" : 124
        },
        {
          "pts" : 57.5,
          "attempts" : 123
        },
        {
          "pts" : 57.5,
          "attempts" : 123
        },
        {
          "pts" : 57.0,
          "attempts" : 123
        },
        {
          "pts" : 57.0,
          "attempts" : 123
        },
        {
          "pts" : 53.5,
          "attempts" : 117
        },
        {
          "pts" : 53.5,
          "attempts" : 117
        },
        {
          "pts" : 53.0,
          "attempts" : 117
        },
        {
          "pts" : 52.5,
          "attempts" : 116
        },
        {
          "pts" : 47.5,
          "attempts" : 108
        },
        {
          "pts" : 44.5,
          "attempts" : 103
        },
        {
          "pts" : 40.5,
          "attempts" : 97
        },
        {
          "pts" : 40.5,
          "attempts" : 97
        },
        {
          "pts" : 39.0,
          "attempts" : 95
        },
        {
          "pts" : 38.0,
          "attempts" : 93
        },
        {
          "pts" : 35.5,
          "attempts" : 89
        },
        {
          "pts" : 28.0,
          "attempts" : 77
        },
        {
          "pts" : 27.5,
          "attempts" : 76
        },
        {
          "pts" : 25.5,
          "attempts" : 73
        },
        {
          "pts" : 22.0,
          "attempts" : 67
        },
        {
          "pts" : 19.0,
          "attempts" : 62
        },
        {
          "pts" : 18.5,
          "attempts" : 61
        }
      ]
    },
    {
      "simulations" : 10222,
      "stats" : [
        {
          "pts" : 181.0,
          "attempts" : 332
        },
        {
          "pts" : 144.0,
          "attempts" : 276
        },
        {
          "pts" : 135.0,
          "attempts" : 262
        },
        {
          "pts" : 134.0,
          "attempts" : 260
        },
        {
          "pts" : 130.0,
          "attempts" : 254
        },
        {
          "pts" : 128.5,
          "attempts" : 252
        },
        {
          "pts" : 112.5,
          "attempts" : 227
        },
        {
          "pts" : 114.5,
          "attempts" : 225
        },
        {
          "pts" : 109.5,
          "attempts" : 222
        },
        {
          "pts" : 108.5,
          "attempts" : 221
        },
        {
          "pts" : 108.5,
          "attempts" : 221
        },
        {
          "pts" : 109.0,
          "attempts" : 221
        },
        {
          "pts" : 108.0,
          "attempts" : 220
        },
        {
          "pts" : 108.0,
          "attempts" : 220
        },
        {
          "pts" : 107.0,
          "attempts" : 218
        },
        {
          "pts" : 103.5,
          "attempts" : 213
        },
        {
          "pts" : 103.5,
          "attempts" : 213
        },
        {
          "pts" : 97.5,
          "attempts" : 203
        },
        {
          "pts" : 95.5,
          "attempts" : 200
        },
        {
          "pts" : 95.0,
          "attempts" : 199
        },
        {
          "pts" : 95.0,
          "attempts" : 199
        },
        {
          "pts" : 95.0,
          "attempts" : 199
        },
        {
          "pts" : 94.0,
          "attempts" : 198
        },
        {
          "pts" : 93.0,
          "attempts" : 196
        },
        {
          "pts" : 90.5,
          "attempts" : 192
        },
        {
          "pts" : 89.5,
          "attempts" : 191
        },
        {
          "pts" : 90.0,
          "attempts" : 191
        },
        {
          "pts" : 86.0,
          "attempts" : 185
        },
        {
          "pts" : 84.0,
          "attempts" : 182
        },
        {
          "pts" : 82.5,
          "attempts" : 179
        },
        {
          "pts" : 80.0,
          "attempts" : 175
        },
        {
          "pts" : 80.0,
          "attempts" : 175
        },
        {
          "pts" : 79.5,
          "attempts" : 175
        },
        {
          "pts" : 77.0,
          "attempts" : 171
        },
        {
          "pts" : 77.0,
          "attempts" : 171
        },
        {
          "pts" : 75.0,
          "attempts" : 167
        },
        {
          "pts" : 75.0,
          "attempts" : 167
        },
        {
          "pts" : 74.5,
          "attempts" : 166
        },
        {
          "pts" : 73.0,
          "attempts" : 164
        },
        {
          "pts" : 70.5,
          "attempts" : 160
        },
        {
          "pts" : 69.0,
          "attempts" : 157
        },
        {
          "pts" : 68.5,
          "attempts" : 157
        },
        {
          "pts" : 66.0,
          "attempts" : 153
        },
        {
          "pts" : 63.5,
          "attempts" : 148
        },
        {
          "pts" : 59.5,
          "attempts" : 142
        },
        {
          "pts" : 56.0,
          "attempts" : 136
        },
        {
          "pts" : 53.5,
          "attempts" : 132
        },
        {
          "pts" : 52.5,
          "attempts" : 130
        },
        {
          "pts" : 51.0,
          "attempts" : 128
        },
        {
          "pts" : 51.5,
          "attempts" : 128
        },
        {
          "pts" : 49.5,
          "attempts" : 125
        },
        {
          "pts" : 46.0,
          "attempts" : 119
        },
        {
          "pts" : 42.5,
          "attempts" : 113
        },
        {
          "pts" : 34.5,
          "attempts" : 99
        },
        {
          "pts" : 31.0,
          "attempts" : 93
        }
      ]
    },
    {
      "simulations" : 11555,
      "stats" : [
        {
          "pts" : 313.5,
          "attempts" : 511
        },
        {
          "pts" : 207.0,
          "attempts" : 359
        },
        {
          "pts" : 204.5,
          "attempts" : 356
        },
        {
          "pts" : 158.5,
          "attempts" : 289
        },
        {
          "pts" : 152.5,
          "attempts" : 280
        },
        {
          "pts" : 149.0,
          "attempts" : 274
        },
        {
          "pts" : 148.0,
          "attempts" : 272
        },
        {
          "pts" : 144.0,
          "attempts" : 267
        },
        {
          "pts" : 137.0,
          "attempts" : 257
        },
        {
          "pts" : 135.5,
          "attempts" : 254
        },
        {
          "pts" : 123.5,
          "attempts" : 236
        },
        {
          "pts" : 122.5,
          "attempts" : 235
        },
        {
          "pts" : 120.0,
          "attempts" : 231
        },
        {
          "pts" : 120.0,
          "attempts" : 231
        },
        {
          "pts" : 119.0,
          "attempts" : 230
        },
        {
          "pts" : 117.5,
          "attempts" : 227
        },
        {
          "pts" : 116.5,
          "attempts" : 226
        },
        {
          "pts" : 112.5,
          "attempts" : 220
        },
        {
          "pts" : 112.0,
          "attempts" : 219
        },
        {
          "pts" : 112.0,
          "attempts" : 219
        },
        {
          "pts" : 111.5,
          "attempts" : 218
        },
        {
          "pts" : 111.5,
          "attempts" : 218
        },
        {
          "pts" : 111.0,
          "attempts" : 217
        },
        {
          "pts" : 108.5,
          "attempts" : 214
        },
        {
          "pts" : 107.5,
          "attempts" : 212
        },
        {
          "pts" : 106.5,
          "attempts" : 211
        },
        {
          "pts" : 106.0,
          "attempts" : 210
        },
        {
          "pts" : 104.5,
          "attempts" : 208
        },
        {
          "pts" : 105.0,
          "attempts" : 208
        },
        {
          "pts" : 102.0,
          "attempts" : 204
        },
        {
          "pts" : 101.5,
          "attempts" : 203
        },
        {
          "pts" : 100.0,
          "attempts" : 201
        },
        {
          "pts" : 99.5,
          "attempts" : 200
        },
        {
          "pts" : 97.0,
          "attempts" : 196
        },
        {
          "pts" : 95.5,
          "attempts" : 194
        },
        {
          "pts" : 94.0,
          "attempts" : 191
        },
        {
          "pts" : 92.5,
          "attempts" : 189
        },
        {
          "pts" : 91.0,
          "attempts" : 187
        },
        {
          "pts" : 91.0,
          "attempts" : 187
        },
        {
          "pts" : 90.0,
          "attempts" : 185
        },
        {
          "pts" : 89.0,
          "attempts" : 184
        },
        {
          "pts" : 84.5,
          "attempts" : 177
        },
        {
          "pts" : 83.5,
          "attempts" : 175
        },
        {
          "pts" : 79.0,
          "attempts" : 168
        },
        {
          "pts" : 78.5,
          "attempts" : 167
        },
        {
          "pts" : 74.0,
          "attempts" : 160
        },
        {
          "pts" : 65.5,
          "attempts" : 147
        },
        {
          "pts" : 65.5,
          "attempts" : 147
        },
        {
          "pts" : 61.5,
          "attempts" : 140
        },
        {
          "pts" : 59.0,
          "attempts" : 136
        },
        {
          "pts" : 57.5,
          "attempts" : 134
        },
        {
          "pts" : 56.5,
          "attempts" : 132
        },
        {
          "pts" : 55.0,
          "attempts" : 130
        },
        {
          "pts" : 44.0,
          "attempts" : 112
        }
      ]
    },
    {
      "simulations" : 14149,
      "stats" : [
        {
          "pts" : 499.5,
          "attempts" : 901
        },
        {
          "pts" : 202.0,
          "attempts" : 416
        },
        {
          "pts" : 162.5,
          "attempts" : 349
        },
        {
          "pts" : 154.0,
          "attempts" : 334
        },
        {
          "pts" : 153.0,
          "attempts" : 333
        },
        {
          "pts" : 151.0,
          "attempts" : 329
        },
        {
          "pts" : 147.0,
          "attempts" : 322
        },
        {
          "pts" : 138.5,
          "attempts" : 308
        },
        {
          "pts" : 138.5,
          "attempts" : 308
        },
        {
          "pts" : 137.5,
          "attempts" : 306
        },
        {
          "pts" : 136.5,
          "attempts" : 304
        },
        {
          "pts" : 135.5,
          "attempts" : 302
        },
        {
          "pts" : 132.0,
          "attempts" : 296
        },
        {
          "pts" : 130.5,
          "attempts" : 294
        },
        {
          "pts" : 129.0,
          "attempts" : 291
        },
        {
          "pts" : 126.0,
          "attempts" : 286
        },
        {
          "pts" : 125.0,
          "attempts" : 284
        },
        {
          "pts" : 122.0,
          "attempts" : 279
        },
        {
          "pts" : 120.5,
          "attempts" : 276
        },
        {
          "pts" : 120.5,
          "attempts" : 276
        },
        {
          "pts" : 120.0,
          "attempts" : 275
        },
        {
          "pts" : 117.0,
          "attempts" : 270
        },
        {
          "pts" : 113.5,
          "attempts" : 264
        },
        {
          "pts" : 112.5,
          "attempts" : 262
        },
        {
          "pts" : 111.0,
          "attempts" : 259
        },
        {
          "pts" : 110.5,
          "attempts" : 258
        },
        {
          "pts" : 109.5,
          "attempts" : 257
        },
        {
          "pts" : 109.0,
          "attempts" : 256
        },
        {
          "pts" : 107.5,
          "attempts" : 253
        },
        {
          "pts" : 106.5,
          "attempts" : 251
        },
        {
          "pts" : 105.5,
          "attempts" : 250
        },
        {
          "pts" : 104.5,
          "attempts" : 248
        },
        {
          "pts" : 102.0,
          "attempts" : 243
        },
        {
          "pts" : 101.0,
          "attempts" : 242
        },
        {
          "pts" : 99.5,
          "attempts" : 239
        },
        {
          "pts" : 94.5,
          "attempts" : 230
        },
        {
          "pts" : 94.0,
          "attempts" : 229
        },
        {
          "pts" : 93.0,
          "attempts" : 227
        },
        {
          "pts" : 92.0,
          "attempts" : 225
        },
        {
          "pts" : 89.5,
          "attempts" : 221
        },
        {
          "pts" : 89.5,
          "attempts" : 221
        },
        {
          "pts" : 87.0,
          "attempts" : 216
        },
        {
          "pts" : 87.0,
          "attempts" : 216
        },
        {
          "pts" : 82.5,
          "attempts" : 208
        },
        {
          "pts" : 81.0,
          "attempts" : 205
        },
        {
          "pts" : 76.5,
          "attempts" : 197
        },
        {
          "pts" : 75.0,
          "attempts" : 194
        },
        {
          "pts" : 65.0,
          "attempts" : 176
        },
        {
          "pts" : 60.5,
          "attempts" : 168
        },
        {
          "pts" : 55.5,
          "attempts" : 158
        },
        {
          "pts" : 51.5,
          "attempts" : 150
        },
        {
          "pts" : 48.0,
          "attempts" : 144
        },
        {
          "pts" : 47.5,
          "attempts" : 143
        }
      ]
    },
    {
      "simulations" : 16263,
      "stats" : [
        {
          "pts" : 435.0,
          "attempts" : 781
        },
        {
          "pts" : 349.5,
          "attempts" : 646
        },
        {
          "pts" : 291.5,
          "attempts" : 553
        },
        {
          "pts" : 264.0,
          "attempts" : 509
        },
        {
          "pts" : 246.0,
          "attempts" : 479
        },
        {
          "pts" : 209.5,
          "attempts" : 420
        },
        {
          "pts" : 193.5,
          "attempts" : 393
        },
        {
          "pts" : 178.0,
          "attempts" : 367
        },
        {
          "pts" : 170.0,
          "attempts" : 354
        },
        {
          "pts" : 169.5,
          "attempts" : 353
        },
        {
          "pts" : 165.0,
          "attempts" : 346
        },
        {
          "pts" : 163.5,
          "attempts" : 343
        },
        {
          "pts" : 163.0,
          "attempts" : 342
        },
        {
          "pts" : 162.5,
          "attempts" : 342
        },
        {
          "pts" : 159.0,
          "attempts" : 336
        },
        {
          "pts" : 156.5,
          "attempts" : 331
        },
        {
          "pts" : 155.0,
          "attempts" : 329
        },
        {
          "pts" : 151.5,
          "attempts" : 323
        },
        {
          "pts" : 144.0,
          "attempts" : 310
        },
        {
          "pts" : 141.5,
          "attempts" : 306
        },
        {
          "pts" : 140.5,
          "attempts" : 304
        },
        {
          "pts" : 139.5,
          "attempts" : 303
        },
        {
          "pts" : 139.0,
          "attempts" : 302
        },
        {
          "pts" : 137.5,
          "attempts" : 299
        },
        {
          "pts" : 135.5,
          "attempts" : 296
        },
        {
          "pts" : 134.5,
          "attempts" : 294
        },
        {
          "pts" : 133.0,
          "attempts" : 292
        },
        {
          "pts" : 131.5,
          "attempts" : 289
        },
        {
          "pts" : 130.0,
          "attempts" : 286
        },
        {
          "pts" : 127.0,
          "attempts" : 281
        },
        {
          "pts" : 125.0,
          "attempts" : 278
        },
        {
          "pts" : 120.0,
          "attempts" : 269
        },
        {
          "pts" : 116.5,
          "attempts" : 263
        },
        {
          "pts" : 116.5,
          "attempts" : 263
        },
        {
          "pts" : 116.0,
          "attempts" : 262
        },
        {
          "pts" : 113.0,
          "attempts" : 257
        },
        {
          "pts" : 111.5,
          "attempts" : 255
        },
        {
          "pts" : 110.5,
          "attempts" : 253
        },
        {
          "pts" : 106.5,
          "attempts" : 246
        },
        {
          "pts" : 106.0,
          "attempts" : 245
        },
        {
          "pts" : 104.0,
          "attempts" : 242
        },
        {
          "pts" : 104.5,
          "attempts" : 242
        },
        {
          "pts" : 101.0,
          "attempts" : 236
        },
        {
          "pts" : 98.0,
          "attempts" : 231
        },
        {
          "pts" : 96.0,
          "attempts" : 228
        },
        {
          "pts" : 94.0,
          "attempts" : 224
        },
        {
          "pts" : 88.5,
          "attempts" : 214
        },
        {
          "pts" : 81.5,
          "attempts" : 202
        },
        {
          "pts" : 79.0,
          "attempts" : 197
        },
        {
          "pts" : 75.0,
          "attempts" : 190
        },
        {
          "pts" : 69.0,
          "attempts" : 179
        },
        {
          "pts" : 68.5,
          "attempts" : 178
        }
      ]
    },
    {
      "simulations" : 7692,
      "stats" : [
        {
          "pts" : 265.5,
          "attempts" : 414
        },
        {
          "pts" : 149.5,
          "attempts" : 256
        },
        {
          "pts" : 144.0,
          "attempts" : 248
        },
        {
          "pts" : 118.5,
          "attempts" : 213
        },
        {
          "pts" : 101.5,
          "attempts" : 188
        },
        {
          "pts" : 97.0,
          "attempts" : 182
        },
        {
          "pts" : 92.0,
          "attempts" : 175
        },
        {
          "pts" : 92.0,
          "attempts" : 175
        },
        {
          "pts" : 89.5,
          "attempts" : 171
        },
        {
          "pts" : 88.5,
          "attempts" : 169
        },
        {
          "pts" : 88.5,
          "attempts" : 169
        },
        {
          "pts" : 84.5,
          "attempts" : 164
        },
        {
          "pts" : 84.5,
          "attempts" : 164
        },
        {
          "pts" : 83.5,
          "attempts" : 162
        },
        {
          "pts" : 83.0,
          "attempts" : 161
        },
        {
          "pts" : 82.5,
          "attempts" : 161
        },
        {
          "pts" : 80.5,
          "attempts" : 158
        },
        {
          "pts" : 81.0,
          "attempts" : 158
        },
        {
          "pts" : 80.5,
          "attempts" : 158
        },
        {
          "pts" : 80.5,
          "attempts" : 158
        },
        {
          "pts" : 79.5,
          "attempts" : 156
        },
        {
          "pts" : 78.5,
          "attempts" : 155
        },
        {
          "pts" : 77.0,
          "attempts" : 153
        },
        {
          "pts" : 76.0,
          "attempts" : 151
        },
        {
          "pts" : 75.5,
          "attempts" : 150
        },
        {
          "pts" : 74.0,
          "attempts" : 148
        },
        {
          "pts" : 73.5,
          "attempts" : 147
        },
        {
          "pts" : 69.5,
          "attempts" : 141
        },
        {
          "pts" : 68.0,
          "attempts" : 139
        },
        {
          "pts" : 66.5,
          "attempts" : 137
        },
        {
          "pts" : 63.5,
          "attempts" : 132
        },
        {
          "pts" : 62.5,
          "attempts" : 131
        },
        {
          "pts" : 62.0,
          "attempts" : 130
        },
        {
          "pts" : 61.0,
          "attempts" : 129
        },
        {
          "pts" : 60.5,
          "attempts" : 128
        },
        {
          "pts" : 60.5,
          "attempts" : 128
        },
        {
          "pts" : 58.5,
          "attempts" : 125
        },
        {
          "pts" : 58.0,
          "attempts" : 124
        },
        {
          "pts" : 58.0,
          "attempts" : 124
        },
        {
          "pts" : 58.0,
          "attempts" : 124
        },
        {
          "pts" : 56.5,
          "attempts" : 122
        },
        {
          "pts" : 56.5,
          "attempts" : 122
        },
        {
          "pts" : 54.5,
          "attempts" : 119
        },
        {
          "pts" : 50.0,
          "attempts" : 112
        },
        {
          "pts" : 44.0,
          "attempts" : 103
        },
        {
          "pts" : 43.5,
          "attempts" : 102
        },
        {
          "pts" : 43.0,
          "attempts" : 101
        },
        {
          "pts" : 41.0,
          "attempts" : 98
        },
        {
          "pts" : 38.0,
          "attempts" : 93
        },
        {
          "pts" : 35.5,
          "attempts" : 89
        },
        {
          "pts" : 27.0,
          "attempts" : 75
        }
      ]
    },
    {
      "simulations" : 5567,
      "stats" : [
        {
          "pts" : 79.5,
          "attempts" : 174
        },
        {
          "pts" : 78.5,
          "attempts" : 172
        },
        {
          "pts" : 70.5,
          "attempts" : 159
        },
        {
          "pts" : 69.0,
          "attempts" : 157
        },
        {
          "pts" : 68.5,
          "attempts" : 156
        },
        {
          "pts" : 68.0,
          "attempts" : 155
        },
        {
          "pts" : 66.0,
          "attempts" : 152
        },
        {
          "pts" : 66.0,
          "attempts" : 152
        },
        {
          "pts" : 62.0,
          "attempts" : 145
        },
        {
          "pts" : 57.0,
          "attempts" : 137
        },
        {
          "pts" : 55.0,
          "attempts" : 134
        },
        {
          "pts" : 54.5,
          "attempts" : 133
        },
        {
          "pts" : 52.5,
          "attempts" : 129
        },
        {
          "pts" : 51.0,
          "attempts" : 127
        },
        {
          "pts" : 51.0,
          "attempts" : 127
        },
        {
          "pts" : 48.5,
          "attempts" : 123
        },
        {
          "pts" : 48.0,
          "attempts" : 122
        },
        {
          "pts" : 47.5,
          "attempts" : 121
        },
        {
          "pts" : 46.0,
          "attempts" : 118
        },
        {
          "pts" : 44.0,
          "attempts" : 115
        },
        {
          "pts" : 41.0,
          "attempts" : 110
        },
        {
          "pts" : 40.5,
          "attempts" : 109
        },
        {
          "pts" : 39.5,
          "attempts" : 107
        },
        {
          "pts" : 38.5,
          "attempts" : 105
        },
        {
          "pts" : 38.5,
          "attempts" : 105
        },
        {
          "pts" : 38.5,
          "attempts" : 105
        },
        {
          "pts" : 38.5,
          "attempts" : 105
        },
        {
          "pts" : 38.0,
          "attempts" : 104
        },
        {
          "pts" : 37.0,
          "attempts" : 103
        },
        {
          "pts" : 36.0,
          "attempts" : 101
        },
        {
          "pts" : 36.0,
          "attempts" : 101
        },
        {
          "pts" : 35.0,
          "attempts" : 99
        },
        {
          "pts" : 33.0,
          "attempts" : 96
        },
        {
          "pts" : 32.5,
          "attempts" : 95
        },
        {
          "pts" : 32.0,
          "attempts" : 94
        },
        {
          "pts" : 32.0,
          "attempts" : 94
        },
        {
          "pts" : 31.5,
          "attempts" : 93
        },
        {
          "pts" : 30.0,
          "attempts" : 90
        },
        {
          "pts" : 30.0,
          "attempts" : 90
        },
        {
          "pts" : 29.5,
          "attempts" : 89
        },
        {
          "pts" : 28.5,
          "attempts" : 87
        },
        {
          "pts" : 28.5,
          "attempts" : 87
        },
        {
          "pts" : 27.0,
          "attempts" : 85
        },
        {
          "pts" : 27.0,
          "attempts" : 85
        },
        {
          "pts" : 25.0,
          "attempts" : 81
        },
        {
          "pts" : 23.5,
          "attempts" : 78
        },
        {
          "pts" : 22.0,
          "attempts" : 75
        },
        {
          "pts" : 20.5,
          "attempts" : 73
        },
        {
          "pts" : 14.0,
          "attempts" : 60
        },
        {
          "pts" : 10.5,
          "attempts" : 53
        }
      ]
    },
    {
      "simulations" : 10052,
      "stats" : [
        {
          "pts" : 503.5,
          "attempts" : 650
        },
        {
          "pts" : 331.0,
          "attempts" : 447
        },
        {
          "pts" : 228.0,
          "attempts" : 324
        },
        {
          "pts" : 220.0,
          "attempts" : 314
        },
        {
          "pts" : 200.5,
          "attempts" : 290
        },
        {
          "pts" : 195.0,
          "attempts" : 284
        },
        {
          "pts" : 194.0,
          "attempts" : 282
        },
        {
          "pts" : 177.0,
          "attempts" : 262
        },
        {
          "pts" : 150.0,
          "attempts" : 228
        },
        {
          "pts" : 149.0,
          "attempts" : 227
        },
        {
          "pts" : 143.0,
          "attempts" : 219
        },
        {
          "pts" : 142.5,
          "attempts" : 219
        },
        {
          "pts" : 140.5,
          "attempts" : 216
        },
        {
          "pts" : 135.5,
          "attempts" : 210
        },
        {
          "pts" : 135.5,
          "attempts" : 210
        },
        {
          "pts" : 131.5,
          "attempts" : 205
        },
        {
          "pts" : 124.5,
          "attempts" : 196
        },
        {
          "pts" : 119.0,
          "attempts" : 189
        },
        {
          "pts" : 118.5,
          "attempts" : 188
        },
        {
          "pts" : 116.0,
          "attempts" : 185
        },
        {
          "pts" : 115.0,
          "attempts" : 184
        },
        {
          "pts" : 114.5,
          "attempts" : 183
        },
        {
          "pts" : 113.0,
          "attempts" : 181
        },
        {
          "pts" : 112.5,
          "attempts" : 181
        },
        {
          "pts" : 111.0,
          "attempts" : 179
        },
        {
          "pts" : 108.5,
          "attempts" : 176
        },
        {
          "pts" : 105.5,
          "attempts" : 172
        },
        {
          "pts" : 106.0,
          "attempts" : 172
        },
        {
          "pts" : 104.5,
          "attempts" : 171
        },
        {
          "pts" : 104.0,
          "attempts" : 170
        },
        {
          "pts" : 104.0,
          "attempts" : 170
        },
        {
          "pts" : 102.5,
          "attempts" : 168
        },
        {
          "pts" : 101.0,
          "attempts" : 166
        },
        {
          "pts" : 99.5,
          "attempts" : 164
        },
        {
          "pts" : 99.0,
          "attempts" : 163
        },
        {
          "pts" : 99.0,
          "attempts" : 163
        },
        {
          "pts" : 96.0,
          "attempts" : 160
        },
        {
          "pts" : 94.5,
          "attempts" : 158
        },
        {
          "pts" : 94.0,
          "attempts" : 157
        },
        {
          "pts" : 92.0,
          "attempts" : 154
        },
        {
          "pts" : 92.0,
          "attempts" : 154
        },
        {
          "pts" : 90.0,
          "attempts" : 152
        },
        {
          "pts" : 89.5,
          "attempts" : 151
        },
        {
          "pts" : 87.5,
          "attempts" : 149
        },
        {
          "pts" : 85.5,
          "attempts" : 146
        },
        {
          "pts" : 84.0,
          "attempts" : 144
        },
        {
          "pts" : 82.0,
          "attempts" : 141
        },
        {
          "pts" : 80.0,
          "attempts" : 139
        },
        {
          "pts" : 80.5,
          "attempts" : 139
        }
      ]
    },
    {
      "simulations" : 12218,
      "stats" : [
        {
          "pts" : 208.0,
          "attempts" : 623
        },
        {
          "pts" : 191.5,
          "attempts" : 583
        },
        {
          "pts" : 144.5,
          "attempts" : 470
        },
        {
          "pts" : 91.0,
          "attempts" : 336
        },
        {
          "pts" : 90.0,
          "attempts" : 333
        },
        {
          "pts" : 85.0,
          "attempts" : 320
        },
        {
          "pts" : 76.5,
          "attempts" : 298
        },
        {
          "pts" : 76.0,
          "attempts" : 297
        },
        {
          "pts" : 73.5,
          "attempts" : 290
        },
        {
          "pts" : 70.0,
          "attempts" : 281
        },
        {
          "pts" : 68.0,
          "attempts" : 276
        },
        {
          "pts" : 67.0,
          "attempts" : 273
        },
        {
          "pts" : 66.5,
          "attempts" : 272
        },
        {
          "pts" : 66.0,
          "attempts" : 271
        },
        {
          "pts" : 65.5,
          "attempts" : 269
        },
        {
          "pts" : 65.0,
          "attempts" : 268
        },
        {
          "pts" : 57.5,
          "attempts" : 245
        },
        {
          "pts" : 56.5,
          "attempts" : 245
        },
        {
          "pts" : 55.5,
          "attempts" : 243
        },
        {
          "pts" : 55.0,
          "attempts" : 241
        },
        {
          "pts" : 55.0,
          "attempts" : 241
        },
        {
          "pts" : 55.0,
          "attempts" : 241
        },
        {
          "pts" : 54.5,
          "attempts" : 240
        },
        {
          "pts" : 54.0,
          "attempts" : 238
        },
        {
          "pts" : 53.0,
          "attempts" : 236
        },
        {
          "pts" : 52.0,
          "attempts" : 233
        },
        {
          "pts" : 50.5,
          "attempts" : 229
        },
        {
          "pts" : 50.0,
          "attempts" : 227
        },
        {
          "pts" : 49.5,
          "attempts" : 226
        },
        {
          "pts" : 49.5,
          "attempts" : 226
        },
        {
          "pts" : 48.0,
          "attempts" : 222
        },
        {
          "pts" : 47.5,
          "attempts" : 221
        },
        {
          "pts" : 45.5,
          "attempts" : 215
        },
        {
          "pts" : 44.0,
          "attempts" : 211
        },
        {
          "pts" : 43.5,
          "attempts" : 210
        },
        {
          "pts" : 42.5,
          "attempts" : 207
        },
        {
          "pts" : 42.0,
          "attempts" : 205
        },
        {
          "pts" : 38.0,
          "attempts" : 194
        },
        {
          "pts" : 37.0,
          "attempts" : 191
        },
        {
          "pts" : 36.5,
          "attempts" : 190
        },
        {
          "pts" : 36.0,
          "attempts" : 188
        },
        {
          "pts" : 35.5,
          "attempts" : 187
        },
        {
          "pts" : 35.0,
          "attempts" : 185
        },
        {
          "pts" : 34.5,
          "attempts" : 184
        },
        {
          "pts" : 32.5,
          "attempts" : 178
        },
        {
          "pts" : 32.5,
          "attempts" : 178
        },
        {
          "pts" : 28.5,
          "attempts" : 167
        },
        {
          "pts" : 11.5,
          "attempts" : 114
        }
      ]
    },
    {
      "simulations" : 42266,
      "stats" : [
        {
          "pts" : 34974.0,
          "attempts" : 34974
        },
        {
          "pts" : 175.0,
          "attempts" : 241
        },
        {
          "pts" : 163.5,
          "attempts" : 228
        },
        {
          "pts" : 163.0,
          "attempts" : 227
        },
        {
          "pts" : 154.0,
          "attempts" : 217
        },
        {
          "pts" : 142.0,
          "attempts" : 203
        },
        {
          "pts" : 138.5,
          "attempts" : 199
        },
        {
          "pts" : 135.5,
          "attempts" : 196
        },
        {
          "pts" : 133.5,
          "attempts" : 193
        },
        {
          "pts" : 132.5,
          "attempts" : 192
        },
        {
          "pts" : 128.0,
          "attempts" : 187
        },
        {
          "pts" : 128.0,
          "attempts" : 187
        },
        {
          "pts" : 121.5,
          "attempts" : 179
        },
        {
          "pts" : 115.5,
          "attempts" : 172
        },
        {
          "pts" : 114.5,
          "attempts" : 171
        },
        {
          "pts" : 111.0,
          "attempts" : 167
        },
        {
          "pts" : 111.0,
          "attempts" : 167
        },
        {
          "pts" : 110.5,
          "attempts" : 166
        },
        {
          "pts" : 108.5,
          "attempts" : 164
        },
        {
          "pts" : 108.0,
          "attempts" : 163
        },
        {
          "pts" : 105.5,
          "attempts" : 160
        },
        {
          "pts" : 103.0,
          "attempts" : 157
        },
        {
          "pts" : 99.5,
          "attempts" : 153
        },
        {
          "pts" : 98.5,
          "attempts" : 152
        },
        {
          "pts" : 95.5,
          "attempts" : 148
        },
        {
          "pts" : 95.0,
          "attempts" : 148
        },
        {
          "pts" : 93.5,
          "attempts" : 146
        },
        {
          "pts" : 92.5,
          "attempts" : 145
        },
        {
          "pts" : 92.0,
          "attempts" : 144
        },
        {
          "pts" : 90.0,
          "attempts" : 142
        },
        {
          "pts" : 90.5,
          "attempts" : 142
        },
        {
          "pts" : 87.5,
          "attempts" : 139
        },
        {
          "pts" : 86.5,
          "attempts" : 138
        },
        {
          "pts" : 86.5,
          "attempts" : 138
        },
        {
          "pts" : 85.5,
          "attempts" : 136
        },
        {
          "pts" : 85.0,
          "attempts" : 136
        },
        {
          "pts" : 85.5,
          "attempts" : 136
        },
        {
          "pts" : 84.5,
          "attempts" : 135
        },
        {
          "pts" : 84.5,
          "attempts" : 135
        },
        {
          "pts" : 83.0,
          "attempts" : 133
        },
        {
          "pts" : 75.5,
          "attempts" : 124
        },
        {
          "pts" : 74.5,
          "attempts" : 123
        },
        {
          "pts" : 74.5,
          "attempts" : 123
        },
        {
          "pts" : 74.0,
          "attempts" : 122
        },
        {
          "pts" : 71.0,
          "attempts" : 119
        },
        {
          "pts" : 65.5,
          "attempts" : 112
        },
        {
          "pts" : 45.5,
          "attempts" : 87
        }
      ]
    }
  ]
}